{"context": {"user": {"countryCode": "CN", "countryName": "China", "locale": "zh_CN", "timeZone": "+08:00", "timeZoneCity": "Australia/Perth"}, "device": {"clazz": null}}, "error": {"detail": null, "isError": "false", "message": null}, "payload": {"league": {"id": "00", "name": "NBA"}, "season": {"isCurrent": "true", "rosterSeasonType": 2, "rosterSeasonYear": "2019", "rosterSeasonYearDisplay": "2019-2020", "scheduleSeasonType": 2, "scheduleSeasonYear": "2019", "scheduleYearDisplay": "2019-2020", "statsSeasonType": 2, "statsSeasonYear": "2019", "statsSeasonYearDisplay": "2019-2020", "year": "2019", "yearDisplay": "2019-2020"}, "leagueSeasonAverage": {"assistsPg": 2.303, "blocksPg": 0.469, "defRebsPg": 3.29, "efficiency": 5.435, "fgaPg": 8.4, "fgmPg": 3.85, "fgpct": 46.0, "foulsPg": 1.95, "ftaPg": 2.15, "ftmPg": 1.65, "ftpct": 77.1, "games": 20, "gamesStarted": null, "minsPg": 22.876, "offRebsPg": 0.959, "pointsPg": 10.545, "rebsPg": 4.248, "stealsPg": 0.724, "tpaPg": 3.2, "tpmPg": 1.15, "tppct": 35.7, "turnoversPg": 1.314}, "player": {"playerProfile": {"code": "khyri_thomas", "country": "\u7f8e\u56fd", "countryEn": "United States", "displayAffiliation": "Creighton/United States", "displayName": "\u51ef\u91cc \u6258\u9a6c\u65af", "displayNameEn": "Khyri Thomas", "dob": "831528000000", "draftYear": "2018", "experience": "1", "firstInitial": "\u51ef\u91cc", "firstName": "\u51ef\u91cc", "firstNameEn": "Khyri", "height": "1.90", "jerseyNo": "13", "lastName": "\u6258\u9a6c\u65af", "lastNameEn": "Thomas", "leagueId": "00", "playerId": "1629017", "position": "\u540e\u536b", "schoolType": "College", "weight": "95.3 \u516c\u65a4"}, "teamProfile": {"abbr": "DET", "city": "\u5e95\u7279\u5f8b", "cityEn": "Detroit", "code": "pistons", "conference": "Eastern", "displayAbbr": "\u6d3b\u585e", "displayConference": "\u4e1c\u90e8", "division": "\u4e2d\u592e\u5206\u533a", "id": "1610612765", "isAllStarTeam": false, "isLeagueTeam": true, "leagueId": "00", "name": "\u6d3b\u585e", "nameEn": "Pistons"}, "stats": {"currentSeasonTypeStat": {"season": {"type": "2", "typeDisplay": "\u5e38\u89c4\u8d5b", "year": "2019", "yearDisplay": "2019-2020"}, "currentSeasonTypePlayerTeamStats": [{"profile": {"abbr": "DET", "city": "\u5e95\u7279\u5f8b", "cityEn": "Detroit", "code": "pistons", "conference": "Eastern", "displayAbbr": "\u6d3b\u585e", "displayConference": "\u4e1c\u90e8", "division": "\u4e2d\u592e\u5206\u533a", "id": "1610612765", "isAllStarTeam": false, "isLeagueTeam": true, "leagueId": "00", "name": "\u6d3b\u585e", "nameEn": "Pistons"}, "statAverage": {"assistsPg": 0.4, "blocksPg": 0.0, "defRebsPg": 0.0, "efficiency": 0.9, "fgaPg": 2.125, "fgmPg": 0.625, "fgpct": 29.4, "foulsPg": 1.1, "ftaPg": 0.5, "ftmPg": 0.25, "ftpct": 50.0, "games": 8, "gamesStarted": 0, "minsPg": 7.7, "offRebsPg": 0.1, "pointsPg": 2.1, "rebsPg": 0.1, "stealsPg": 0.3, "tpaPg": 1.75, "tpmPg": 0.625, "tppct": 35.7, "turnoversPg": 0.3}, "statTotal": {"assists": 3, "blocks": 0, "defRebs": 0, "fga": 17, "fgm": 5, "fgpct": 29.4, "fouls": 9, "fta": 4, "ftm": 2, "ftpct": 50.0, "mins": 61, "offRebs": 1, "points": 17, "rebs": 1, "secs": 0, "steals": 3, "tpa": 14, "tpm": 5, "tppct": 35.7, "turnovers": 3}, "round": null, "roundText": null}]}, "regularSeasonStat": {"playerTeams": [{"profile": {"abbr": "DET", "city": "\u5e95\u7279\u5f8b", "cityEn": "Detroit", "code": "pistons", "conference": "Eastern", "displayAbbr": "\u6d3b\u585e", "displayConference": "\u4e1c\u90e8", "division": "\u4e2d\u592e\u5206\u533a", "id": "1610612765", "isAllStarTeam": false, "isLeagueTeam": true, "leagueId": "00", "name": "\u6d3b\u585e", "nameEn": "Pistons"}, "statAverage": {"assistsPg": 0.3, "blocksPg": 0.1, "defRebsPg": 0.6, "efficiency": 1.8, "fgaPg": 2.654, "fgmPg": 0.846, "fgpct": 31.9, "foulsPg": 0.8, "ftaPg": 0.423, "ftmPg": 0.269, "ftpct": 63.6, "games": 26, "gamesStarted": 0, "minsPg": 7.5, "offRebsPg": 0.2, "pointsPg": 2.3, "rebsPg": 0.8, "stealsPg": 0.2, "tpaPg": 1.346, "tpmPg": 0.385, "tppct": 28.6, "turnoversPg": 0.1}, "statTotal": {"assists": 8, "blocks": 5, "defRebs": 16, "fga": 69, "fgm": 22, "fgpct": 31.9, "fouls": 22, "fta": 11, "ftm": 7, "ftpct": 63.6, "mins": 195, "offRebs": 4, "points": 61, "rebs": 20, "secs": 0, "steals": 7, "tpa": 35, "tpm": 10, "tppct": 28.6, "turnovers": 4}, "season": "2018"}, {"profile": {"abbr": "DET", "city": "\u5e95\u7279\u5f8b", "cityEn": "Detroit", "code": "pistons", "conference": "Eastern", "displayAbbr": "\u6d3b\u585e", "displayConference": "\u4e1c\u90e8", "division": "\u4e2d\u592e\u5206\u533a", "id": "1610612765", "isAllStarTeam": false, "isLeagueTeam": true, "leagueId": "00", "name": "\u6d3b\u585e", "nameEn": "Pistons"}, "statAverage": {"assistsPg": 0.4, "blocksPg": 0.0, "defRebsPg": 0.0, "efficiency": 0.9, "fgaPg": 2.125, "fgmPg": 0.625, "fgpct": 29.4, "foulsPg": 1.1, "ftaPg": 0.5, "ftmPg": 0.25, "ftpct": 50.0, "games": 8, "gamesStarted": 0, "minsPg": 7.7, "offRebsPg": 0.1, "pointsPg": 2.1, "rebsPg": 0.1, "stealsPg": 0.3, "tpaPg": 1.75, "tpmPg": 0.625, "tppct": 35.7, "turnoversPg": 0.3}, "statTotal": {"assists": 3, "blocks": 0, "defRebs": 0, "fga": 17, "fgm": 5, "fgpct": 29.4, "fouls": 9, "fta": 4, "ftm": 2, "ftpct": 50.0, "mins": 61, "offRebs": 1, "points": 17, "rebs": 1, "secs": 0, "steals": 3, "tpa": 14, "tpm": 5, "tppct": 35.7, "turnovers": 3}, "season": "2019"}]}, "playoffStat": {"playerTeams": [{"profile": {"abbr": "DET", "city": "\u5e95\u7279\u5f8b", "cityEn": "Detroit", "code": "pistons", "conference": "Eastern", "displayAbbr": "\u6d3b\u585e", "displayConference": "\u4e1c\u90e8", "division": "\u4e2d\u592e\u5206\u533a", "id": "1610612765", "isAllStarTeam": false, "isLeagueTeam": true, "leagueId": "00", "name": "\u6d3b\u585e", "nameEn": "Pistons"}, "statAverage": {"assistsPg": 0.0, "blocksPg": 0.0, "defRebsPg": 0.7, "efficiency": 4.0, "fgaPg": 4.0, "fgmPg": 2.0, "fgpct": 50.0, "foulsPg": 0.0, "ftaPg": 0.333, "ftmPg": 0.333, "ftpct": 100.0, "games": 3, "gamesStarted": 0, "minsPg": 5.0, "offRebsPg": 0.0, "pointsPg": 4.7, "rebsPg": 0.7, "stealsPg": 0.6, "tpaPg": 1.333, "tpmPg": 0.333, "tppct": 25.0, "turnoversPg": 0.0}, "statTotal": {"assists": 0, "blocks": 0, "defRebs": 2, "fga": 12, "fgm": 6, "fgpct": 50.0, "fouls": 0, "fta": 1, "ftm": 1, "ftpct": 100.0, "mins": 15, "offRebs": 0, "points": 14, "rebs": 2, "secs": 0, "steals": 2, "tpa": 4, "tpm": 1, "tppct": 25.0, "turnovers": 0}, "season": "2018"}]}, "allStarStat": {"playerTeams": []}, "seasonGames": [{"profile": {"teamProfile": {"abbr": "DET", "city": "\u5e95\u7279\u5f8b", "cityEn": "Detroit", "code": "pistons", "conference": "Eastern", "displayAbbr": "\u6d3b\u585e", "displayConference": "\u4e1c\u90e8", "division": "\u4e2d\u592e\u5206\u533a", "id": "1610612765", "isAllStarTeam": false, "isLeagueTeam": true, "leagueId": "00", "name": "\u6d3b\u585e", "nameEn": "Pistons"}, "oppTeamProfile": {"abbr": "PHI", "city": "\u8d39\u57ce", "cityEn": "Philadelphia", "code": "sixers", "conference": "Eastern", "displayAbbr": "76\u4eba", "displayConference": "\u4e1c\u90e8", "division": "\u5927\u897f\u6d0b\u5206\u533a", "id": "1610612755", "isAllStarTeam": false, "isLeagueTeam": true, "leagueId": "00", "name": "76\u4eba", "nameEn": "Sixers"}, "gameId": "0021900971", "isHome": "false", "oppTeamScore": 124, "teamScore": 106, "utcMillis": "1583967600000", "winOrLoss": "Lost"}, "statTotal": {"assists": 1, "blocks": 0, "defRebs": 0, "fga": 3, "fgm": 1, "fgpct": 33.3, "fouls": 4, "fta": 2, "ftm": 1, "ftpct": 50.0, "mins": 14, "offRebs": 0, "points": 4, "rebs": 0, "secs": 24, "steals": 1, "tpa": 3, "tpm": 1, "tppct": 33.3, "turnovers": 0}}, {"profile": {"teamProfile": {"abbr": "DET", "city": "\u5e95\u7279\u5f8b", "cityEn": "Detroit", "code": "pistons", "conference": "Eastern", "displayAbbr": "\u6d3b\u585e", "displayConference": "\u4e1c\u90e8", "division": "\u4e2d\u592e\u5206\u533a", "id": "1610612765", "isAllStarTeam": false, "isLeagueTeam": true, "leagueId": "00", "name": "\u6d3b\u585e", "nameEn": "Pistons"}, "oppTeamProfile": {"abbr": "NYK", "city": "\u7ebd\u7ea6", "cityEn": "New York", "code": "knicks", "conference": "Eastern", "displayAbbr": "\u5c3c\u514b\u65af", "displayConference": "\u4e1c\u90e8", "division": "\u5927\u897f\u6d0b\u5206\u533a", "id": "1610612752", "isAllStarTeam": false, "isLeagueTeam": true, "leagueId": "00", "name": "\u5c3c\u514b\u65af", "nameEn": "Knicks"}, "gameId": "0021900955", "isHome": "false", "oppTeamScore": 96, "teamScore": 84, "utcMillis": "1583710200000", "winOrLoss": "Lost"}, "statTotal": {"assists": 0, "blocks": 0, "defRebs": 0, "fga": 6, "fgm": 2, "fgpct": 33.3, "fouls": 2, "fta": 0, "ftm": 0, "ftpct": 0.0, "mins": 13, "offRebs": 1, "points": 6, "rebs": 1, "secs": 54, "steals": 0, "tpa": 4, "tpm": 2, "tppct": 50.0, "turnovers": 1}}, {"profile": {"teamProfile": {"abbr": "DET", "city": "\u5e95\u7279\u5f8b", "cityEn": "Detroit", "code": "pistons", "conference": "Eastern", "displayAbbr": "\u6d3b\u585e", "displayConference": "\u4e1c\u90e8", "division": "\u4e2d\u592e\u5206\u533a", "id": "1610612765", "isAllStarTeam": false, "isLeagueTeam": true, "leagueId": "00", "name": "\u6d3b\u585e", "nameEn": "Pistons"}, "oppTeamProfile": {"abbr": "UTA", "city": "\u72b9\u4ed6", "cityEn": "Utah", "code": "jazz", "conference": "Western", "displayAbbr": "\u7235\u58eb", "displayConference": "\u897f\u90e8", "division": "\u897f\u5317\u5206\u533a", "id": "1610612762", "isAllStarTeam": false, "isLeagueTeam": true, "leagueId": "00", "name": "\u7235\u58eb", "nameEn": "Jazz"}, "gameId": "0021900941", "isHome": "true", "oppTeamScore": 111, "teamScore": 105, "utcMillis": "1583625600000", "winOrLoss": "Lost"}, "statTotal": {"assists": 0, "blocks": 0, "defRebs": 0, "fga": 0, "fgm": 0, "fgpct": 0.0, "fouls": 0, "fta": 0, "ftm": 0, "ftpct": 0.0, "mins": 0, "offRebs": 0, "points": 0, "rebs": 0, "secs": 0, "steals": 0, "tpa": 0, "tpm": 0, "tppct": 0.0, "turnovers": 0}}, {"profile": {"teamProfile": {"abbr": "DET", "city": "\u5e95\u7279\u5f8b", "cityEn": "Detroit", "code": "pistons", "conference": "Eastern", "displayAbbr": "\u6d3b\u585e", "displayConference": "\u4e1c\u90e8", "division": "\u4e2d\u592e\u5206\u533a", "id": "1610612765", "isAllStarTeam": false, "isLeagueTeam": true, "leagueId": "00", "name": "\u6d3b\u585e", "nameEn": "Pistons"}, "oppTeamProfile": {"abbr": "OKC", "city": "\u4fc4\u514b\u62c9\u8377\u9a6c\u57ce", "cityEn": "Oklahoma City", "code": "thunder", "conference": "Western", "displayAbbr": "\u96f7\u9706", "displayConference": "\u897f\u90e8", "division": "\u897f\u5317\u5206\u533a", "id": "1610612760", "isAllStarTeam": false, "isLeagueTeam": true, "leagueId": "00", "name": "\u96f7\u9706", "nameEn": "Thunder"}, "gameId": "0021900918", "isHome": "true", "oppTeamScore": 114, "teamScore": 107, "utcMillis": "1583366400000", "winOrLoss": "Lost"}, "statTotal": {"assists": 1, "blocks": 0, "defRebs": 0, "fga": 2, "fgm": 0, "fgpct": 0.0, "fouls": 0, "fta": 0, "ftm": 0, "ftpct": 0.0, "mins": 9, "offRebs": 0, "points": 0, "rebs": 0, "secs": 38, "steals": 1, "tpa": 2, "tpm": 0, "tppct": 0.0, "turnovers": 1}}, {"profile": {"teamProfile": {"abbr": "DET", "city": "\u5e95\u7279\u5f8b", "cityEn": "Detroit", "code": "pistons", "conference": "Eastern", "displayAbbr": "\u6d3b\u585e", "displayConference": "\u4e1c\u90e8", "division": "\u4e2d\u592e\u5206\u533a", "id": "1610612765", "isAllStarTeam": false, "isLeagueTeam": true, "leagueId": "00", "name": "\u6d3b\u585e", "nameEn": "Pistons"}, "oppTeamProfile": {"abbr": "SAC", "city": "\u8428\u514b\u62c9\u95e8\u6258", "cityEn": "Sacramento", "code": "kings", "conference": "Western", "displayAbbr": "\u56fd\u738b", "displayConference": "\u897f\u90e8", "division": "\u592a\u5e73\u6d0b\u5206\u533a", "id": "1610612758", "isAllStarTeam": false, "isLeagueTeam": true, "leagueId": "00", "name": "\u56fd\u738b", "nameEn": "Kings"}, "gameId": "0021900899", "isHome": "false", "oppTeamScore": 106, "teamScore": 100, "utcMillis": "1583103600000", "winOrLoss": "Lost"}, "statTotal": {"assists": 0, "blocks": 0, "defRebs": 0, "fga": 1, "fgm": 0, "fgpct": 0.0, "fouls": 1, "fta": 0, "ftm": 0, "ftpct": 0.0, "mins": 4, "offRebs": 0, "points": 0, "rebs": 0, "secs": 47, "steals": 1, "tpa": 1, "tpm": 0, "tppct": 0.0, "turnovers": 0}}, {"profile": {"teamProfile": {"abbr": "DET", "city": "\u5e95\u7279\u5f8b", "cityEn": "Detroit", "code": "pistons", "conference": "Eastern", "displayAbbr": "\u6d3b\u585e", "displayConference": "\u4e1c\u90e8", "division": "\u4e2d\u592e\u5206\u533a", "id": "1610612765", "isAllStarTeam": false, "isLeagueTeam": true, "leagueId": "00", "name": "\u6d3b\u585e", "nameEn": "Pistons"}, "oppTeamProfile": {"abbr": "PHX", "city": "\u83f2\u5c3c\u514b\u65af", "cityEn": "Phoenix", "code": "suns", "conference": "Western", "displayAbbr": "\u592a\u9633", "displayConference": "\u897f\u90e8", "division": "\u592a\u5e73\u6d0b\u5206\u533a", "id": "1610612756", "isAllStarTeam": false, "isLeagueTeam": true, "leagueId": "00", "name": "\u592a\u9633", "nameEn": "Suns"}, "gameId": "0021900884", "isHome": "false", "oppTeamScore": 111, "teamScore": 113, "utcMillis": "1582941600000", "winOrLoss": "Won"}, "statTotal": {"assists": 0, "blocks": 0, "defRebs": 0, "fga": 1, "fgm": 1, "fgpct": 100.0, "fouls": 0, "fta": 0, "ftm": 0, "ftpct": 0.0, "mins": 2, "offRebs": 0, "points": 3, "rebs": 0, "secs": 1, "steals": 0, "tpa": 1, "tpm": 1, "tppct": 100.0, "turnovers": 0}}, {"profile": {"teamProfile": {"abbr": "DET", "city": "\u5e95\u7279\u5f8b", "cityEn": "Detroit", "code": "pistons", "conference": "Eastern", "displayAbbr": "\u6d3b\u585e", "displayConference": "\u4e1c\u90e8", "division": "\u4e2d\u592e\u5206\u533a", "id": "1610612765", "isAllStarTeam": false, "isLeagueTeam": true, "leagueId": "00", "name": "\u6d3b\u585e", "nameEn": "Pistons"}, "oppTeamProfile": {"abbr": "DEN", "city": "\u4e39\u4f5b", "cityEn": "Denver", "code": "nuggets", "conference": "Western", "displayAbbr": "\u6398\u91d1", "displayConference": "\u897f\u90e8", "division": "\u897f\u5317\u5206\u533a", "id": "1610612743", "isAllStarTeam": false, "isLeagueTeam": true, "leagueId": "00", "name": "\u6398\u91d1", "nameEn": "Nuggets"}, "gameId": "0021900860", "isHome": "false", "oppTeamScore": 115, "teamScore": 98, "utcMillis": "1582682400000", "winOrLoss": "Lost"}, "statTotal": {"assists": 1, "blocks": 0, "defRebs": 0, "fga": 4, "fgm": 1, "fgpct": 25.0, "fouls": 2, "fta": 0, "ftm": 0, "ftpct": 0.0, "mins": 14, "offRebs": 0, "points": 3, "rebs": 0, "secs": 51, "steals": 0, "tpa": 3, "tpm": 1, "tppct": 33.3, "turnovers": 1}}, {"profile": {"teamProfile": {"abbr": "DET", "city": "\u5e95\u7279\u5f8b", "cityEn": "Detroit", "code": "pistons", "conference": "Eastern", "displayAbbr": "\u6d3b\u585e", "displayConference": "\u4e1c\u90e8", "division": "\u4e2d\u592e\u5206\u533a", "id": "1610612765", "isAllStarTeam": false, "isLeagueTeam": true, "leagueId": "00", "name": "\u6d3b\u585e", "nameEn": "Pistons"}, "oppTeamProfile": {"abbr": "IND", "city": "\u5370\u7b2c\u5b89\u7eb3", "cityEn": "Indiana", "code": "pacers", "conference": "Eastern", "displayAbbr": "\u6b65\u884c\u8005", "displayConference": "\u4e1c\u90e8", "division": "\u4e2d\u592e\u5206\u533a", "id": "1610612754", "isAllStarTeam": false, "isLeagueTeam": true, "leagueId": "00", "name": "\u6b65\u884c\u8005", "nameEn": "Pacers"}, "gameId": "0021900116", "isHome": "false", "oppTeamScore": 112, "teamScore": 106, "utcMillis": "1573257600000", "winOrLoss": "Lost"}, "statTotal": {"assists": 0, "blocks": 0, "defRebs": 0, "fga": 0, "fgm": 0, "fgpct": 0.0, "fouls": 0, "fta": 0, "ftm": 0, "ftpct": 0.0, "mins": 0, "offRebs": 0, "points": 0, "rebs": 0, "secs": 0, "steals": 0, "tpa": 0, "tpm": 0, "tppct": 0.0, "turnovers": 0}}, {"profile": {"teamProfile": {"abbr": "DET", "city": "\u5e95\u7279\u5f8b", "cityEn": "Detroit", "code": "pistons", "conference": "Eastern", "displayAbbr": "\u6d3b\u585e", "displayConference": "\u4e1c\u90e8", "division": "\u4e2d\u592e\u5206\u533a", "id": "1610612765", "isAllStarTeam": false, "isLeagueTeam": true, "leagueId": "00", "name": "\u6d3b\u585e", "nameEn": "Pistons"}, "oppTeamProfile": {"abbr": "NYK", "city": "\u7ebd\u7ea6", "cityEn": "New York", "code": "knicks", "conference": "Eastern", "displayAbbr": "\u5c3c\u514b\u65af", "displayConference": "\u4e1c\u90e8", "division": "\u5927\u897f\u6d0b\u5206\u533a", "id": "1610612752", "isAllStarTeam": false, "isLeagueTeam": true, "leagueId": "00", "name": "\u5c3c\u514b\u65af", "nameEn": "Knicks"}, "gameId": "0021900103", "isHome": "true", "oppTeamScore": 102, "teamScore": 122, "utcMillis": "1573084800000", "winOrLoss": "Won"}, "statTotal": {"assists": 0, "blocks": 0, "defRebs": 0, "fga": 0, "fgm": 0, "fgpct": 0.0, "fouls": 0, "fta": 2, "ftm": 1, "ftpct": 50.0, "mins": 4, "offRebs": 0, "points": 1, "rebs": 0, "secs": 43, "steals": 0, "tpa": 0, "tpm": 0, "tppct": 0.0, "turnovers": 0}}, {"profile": {"teamProfile": {"abbr": "DET", "city": "\u5e95\u7279\u5f8b", "cityEn": "Detroit", "code": "pistons", "conference": "Eastern", "displayAbbr": "\u6d3b\u585e", "displayConference": "\u4e1c\u90e8", "division": "\u4e2d\u592e\u5206\u533a", "id": "1610612765", "isAllStarTeam": false, "isLeagueTeam": true, "leagueId": "00", "name": "\u6d3b\u585e", "nameEn": "Pistons"}, "oppTeamProfile": {"abbr": "WAS", "city": "\u534e\u76db\u987f", "cityEn": "Washington", "code": "wizards", "conference": "Eastern", "displayAbbr": "\u5947\u624d", "displayConference": "\u4e1c\u90e8", "division": "\u4e1c\u5357\u5206\u533a", "id": "1610612764", "isAllStarTeam": false, "isLeagueTeam": true, "leagueId": "00", "name": "\u5947\u624d", "nameEn": "Wizards"}, "gameId": "0021900091", "isHome": "false", "oppTeamScore": 115, "teamScore": 99, "utcMillis": "1572912000000", "winOrLoss": "Lost"}, "statTotal": {"assists": 0, "blocks": 0, "defRebs": 0, "fga": 0, "fgm": 0, "fgpct": 0.0, "fouls": 0, "fta": 0, "ftm": 0, "ftpct": 0.0, "mins": 2, "offRebs": 0, "points": 0, "rebs": 0, "secs": 54, "steals": 0, "tpa": 0, "tpm": 0, "tppct": 0.0, "turnovers": 0}}, {"profile": {"teamProfile": {"abbr": "DET", "city": "\u5e95\u7279\u5f8b", "cityEn": "Detroit", "code": "pistons", "conference": "Eastern", "displayAbbr": "\u6d3b\u585e", "displayConference": "\u4e1c\u90e8", "division": "\u4e2d\u592e\u5206\u533a", "id": "1610612765", "isAllStarTeam": false, "isLeagueTeam": true, "leagueId": "00", "name": "\u6d3b\u585e", "nameEn": "Pistons"}, "oppTeamProfile": {"abbr": "BKN", "city": "\u5e03\u9c81\u514b\u6797", "cityEn": "Brooklyn", "code": "nets", "conference": "Eastern", "displayAbbr": "\u7bee\u7f51", "displayConference": "\u4e1c\u90e8", "division": "\u5927\u897f\u6d0b\u5206\u533a", "id": "1610612751", "isAllStarTeam": false, "isLeagueTeam": true, "leagueId": "00", "name": "\u7bee\u7f51", "nameEn": "Nets"}, "gameId": "0021900078", "isHome": "true", "oppTeamScore": 109, "teamScore": 113, "utcMillis": "1572735600000", "winOrLoss": "Won"}, "statTotal": {"assists": 0, "blocks": 0, "defRebs": 0, "fga": 0, "fgm": 0, "fgpct": 0.0, "fouls": 0, "fta": 0, "ftm": 0, "ftpct": 0.0, "mins": 0, "offRebs": 0, "points": 0, "rebs": 0, "secs": 0, "steals": 0, "tpa": 0, "tpm": 0, "tppct": 0.0, "turnovers": 0}}, {"profile": {"teamProfile": {"abbr": "DET", "city": "\u5e95\u7279\u5f8b", "cityEn": "Detroit", "code": "pistons", "conference": "Eastern", "displayAbbr": "\u6d3b\u585e", "displayConference": "\u4e1c\u90e8", "division": "\u4e2d\u592e\u5206\u533a", "id": "1610612765", "isAllStarTeam": false, "isLeagueTeam": true, "leagueId": "00", "name": "\u6d3b\u585e", "nameEn": "Pistons"}, "oppTeamProfile": {"abbr": "CHI", "city": "\u829d\u52a0\u54e5", "cityEn": "Chicago", "code": "bulls", "conference": "Eastern", "displayAbbr": "\u516c\u725b", "displayConference": "\u4e1c\u90e8", "division": "\u4e2d\u592e\u5206\u533a", "id": "1610612741", "isAllStarTeam": false, "isLeagueTeam": true, "leagueId": "00", "name": "\u516c\u725b", "nameEn": "Bulls"}, "gameId": "0021900073", "isHome": "false", "oppTeamScore": 112, "teamScore": 106, "utcMillis": "1572652800000", "winOrLoss": "Lost"}, "statTotal": {"assists": 0, "blocks": 0, "defRebs": 0, "fga": 0, "fgm": 0, "fgpct": 0.0, "fouls": 0, "fta": 0, "ftm": 0, "ftpct": 0.0, "mins": 0, "offRebs": 0, "points": 0, "rebs": 0, "secs": 0, "steals": 0, "tpa": 0, "tpm": 0, "tppct": 0.0, "turnovers": 0}}, {"profile": {"teamProfile": {"abbr": "DET", "city": "\u5e95\u7279\u5f8b", "cityEn": "Detroit", "code": "pistons", "conference": "Eastern", "displayAbbr": "\u6d3b\u585e", "displayConference": "\u4e1c\u90e8", "division": "\u4e2d\u592e\u5206\u533a", "id": "1610612765", "isAllStarTeam": false, "isLeagueTeam": true, "leagueId": "00", "name": "\u6d3b\u585e", "nameEn": "Pistons"}, "oppTeamProfile": {"abbr": "TOR", "city": "\u591a\u4f26\u591a", "cityEn": "Toronto", "code": "raptors", "conference": "Eastern", "displayAbbr": "\u731b\u9f99", "displayConference": "\u4e1c\u90e8", "division": "\u5927\u897f\u6d0b\u5206\u533a", "id": "1610612761", "isAllStarTeam": false, "isLeagueTeam": true, "leagueId": "00", "name": "\u731b\u9f99", "nameEn": "Raptors"}, "gameId": "0021900060", "isHome": "false", "oppTeamScore": 125, "teamScore": 113, "utcMillis": "1572478200000", "winOrLoss": "Lost"}, "statTotal": {"assists": 0, "blocks": 0, "defRebs": 0, "fga": 0, "fgm": 0, "fgpct": 0.0, "fouls": 0, "fta": 0, "ftm": 0, "ftpct": 0.0, "mins": 0, "offRebs": 0, "points": 0, "rebs": 0, "secs": 0, "steals": 0, "tpa": 0, "tpm": 0, "tppct": 0.0, "turnovers": 0}}, {"profile": {"teamProfile": {"abbr": "DET", "city": "\u5e95\u7279\u5f8b", "cityEn": "Detroit", "code": "pistons", "conference": "Eastern", "displayAbbr": "\u6d3b\u585e", "displayConference": "\u4e1c\u90e8", "division": "\u4e2d\u592e\u5206\u533a", "id": "1610612765", "isAllStarTeam": false, "isLeagueTeam": true, "leagueId": "00", "name": "\u6d3b\u585e", "nameEn": "Pistons"}, "oppTeamProfile": {"abbr": "IND", "city": "\u5370\u7b2c\u5b89\u7eb3", "cityEn": "Indiana", "code": "pacers", "conference": "Eastern", "displayAbbr": "\u6b65\u884c\u8005", "displayConference": "\u4e1c\u90e8", "division": "\u4e2d\u592e\u5206\u533a", "id": "1610612754", "isAllStarTeam": false, "isLeagueTeam": true, "leagueId": "00", "name": "\u6b65\u884c\u8005", "nameEn": "Pacers"}, "gameId": "0021900041", "isHome": "true", "oppTeamScore": 94, "teamScore": 96, "utcMillis": "1572303600000", "winOrLoss": "Won"}, "statTotal": {"assists": 0, "blocks": 0, "defRebs": 0, "fga": 0, "fgm": 0, "fgpct": 0.0, "fouls": 0, "fta": 0, "ftm": 0, "ftpct": 0.0, "mins": 0, "offRebs": 0, "points": 0, "rebs": 0, "secs": 0, "steals": 0, "tpa": 0, "tpm": 0, "tppct": 0.0, "turnovers": 0}}, {"profile": {"teamProfile": {"abbr": "DET", "city": "\u5e95\u7279\u5f8b", "cityEn": "Detroit", "code": "pistons", "conference": "Eastern", "displayAbbr": "\u6d3b\u585e", "displayConference": "\u4e1c\u90e8", "division": "\u4e2d\u592e\u5206\u533a", "id": "1610612765", "isAllStarTeam": false, "isLeagueTeam": true, "leagueId": "00", "name": "\u6d3b\u585e", "nameEn": "Pistons"}, "oppTeamProfile": {"abbr": "PHI", "city": "\u8d39\u57ce", "cityEn": "Philadelphia", "code": "sixers", "conference": "Eastern", "displayAbbr": "76\u4eba", "displayConference": "\u4e1c\u90e8", "division": "\u5927\u897f\u6d0b\u5206\u533a", "id": "1610612755", "isAllStarTeam": false, "isLeagueTeam": true, "leagueId": "00", "name": "76\u4eba", "nameEn": "Sixers"}, "gameId": "0021900027", "isHome": "true", "oppTeamScore": 117, "teamScore": 111, "utcMillis": "1572130800000", "winOrLoss": "Lost"}, "statTotal": {"assists": 0, "blocks": 0, "defRebs": 0, "fga": 0, "fgm": 0, "fgpct": 0.0, "fouls": 0, "fta": 0, "ftm": 0, "ftpct": 0.0, "mins": 0, "offRebs": 0, "points": 0, "rebs": 0, "secs": 0, "steals": 0, "tpa": 0, "tpm": 0, "tppct": 0.0, "turnovers": 0}}, {"profile": {"teamProfile": {"abbr": "DET", "city": "\u5e95\u7279\u5f8b", "cityEn": "Detroit", "code": "pistons", "conference": "Eastern", "displayAbbr": "\u6d3b\u585e", "displayConference": "\u4e1c\u90e8", "division": "\u4e2d\u592e\u5206\u533a", "id": "1610612765", "isAllStarTeam": false, "isLeagueTeam": true, "leagueId": "00", "name": "\u6d3b\u585e", "nameEn": "Pistons"}, "oppTeamProfile": {"abbr": "ATL", "city": "\u4e9a\u7279\u5170\u5927", "cityEn": "Atlanta", "code": "hawks", "conference": "Eastern", "displayAbbr": "\u8001\u9e70", "displayConference": "\u4e1c\u90e8", "division": "\u4e1c\u5357\u5206\u533a", "id": "1610612737", "isAllStarTeam": false, "isLeagueTeam": true, "leagueId": "00", "name": "\u8001\u9e70", "nameEn": "Hawks"}, "gameId": "0021900014", "isHome": "true", "oppTeamScore": 117, "teamScore": 100, "utcMillis": "1571958000000", "winOrLoss": "Lost"}, "statTotal": {"assists": 0, "blocks": 0, "defRebs": 0, "fga": 0, "fgm": 0, "fgpct": 0.0, "fouls": 0, "fta": 0, "ftm": 0, "ftpct": 0.0, "mins": 0, "offRebs": 0, "points": 0, "rebs": 0, "secs": 0, "steals": 0, "tpa": 0, "tpm": 0, "tppct": 0.0, "turnovers": 0}}, {"profile": {"teamProfile": {"abbr": "DET", "city": "\u5e95\u7279\u5f8b", "cityEn": "Detroit", "code": "pistons", "conference": "Eastern", "displayAbbr": "\u6d3b\u585e", "displayConference": "\u4e1c\u90e8", "division": "\u4e2d\u592e\u5206\u533a", "id": "1610612765", "isAllStarTeam": false, "isLeagueTeam": true, "leagueId": "00", "name": "\u6d3b\u585e", "nameEn": "Pistons"}, "oppTeamProfile": {"abbr": "IND", "city": "\u5370\u7b2c\u5b89\u7eb3", "cityEn": "Indiana", "code": "pacers", "conference": "Eastern", "displayAbbr": "\u6b65\u884c\u8005", "displayConference": "\u4e1c\u90e8", "division": "\u4e2d\u592e\u5206\u533a", "id": "1610612754", "isAllStarTeam": false, "isLeagueTeam": true, "leagueId": "00", "name": "\u6b65\u884c\u8005", "nameEn": "Pacers"}, "gameId": "0021900004", "isHome": "false", "oppTeamScore": 110, "teamScore": 119, "utcMillis": "1571871600000", "winOrLoss": "Won"}, "statTotal": {"assists": 0, "blocks": 0, "defRebs": 0, "fga": 0, "fgm": 0, "fgpct": 0.0, "fouls": 0, "fta": 0, "ftm": 0, "ftpct": 0.0, "mins": 0, "offRebs": 0, "points": 0, "rebs": 0, "secs": 0, "steals": 0, "tpa": 0, "tpm": 0, "tppct": 0.0, "turnovers": 0}}, {"profile": {"teamProfile": {"abbr": "DET", "city": "\u5e95\u7279\u5f8b", "cityEn": "Detroit", "code": "pistons", "conference": "Eastern", "displayAbbr": "\u6d3b\u585e", "displayConference": "\u4e1c\u90e8", "division": "\u4e2d\u592e\u5206\u533a", "id": "1610612765", "isAllStarTeam": false, "isLeagueTeam": true, "leagueId": "00", "name": "\u6d3b\u585e", "nameEn": "Pistons"}, "oppTeamProfile": {"abbr": "CHA", "city": "\u590f\u6d1b\u7279", "cityEn": "Charlotte", "code": "hornets", "conference": "Eastern", "displayAbbr": "\u9ec4\u8702", "displayConference": "\u4e1c\u90e8", "division": "\u4e1c\u5357\u5206\u533a", "id": "1610612766", "isAllStarTeam": false, "isLeagueTeam": true, "leagueId": "00", "name": "\u9ec4\u8702", "nameEn": "Hornets"}, "gameId": "0011900062", "isHome": "false", "oppTeamScore": 110, "teamScore": 116, "utcMillis": "1571266800000", "winOrLoss": "Won"}, "statTotal": {"assists": 0, "blocks": 0, "defRebs": 0, "fga": 0, "fgm": 0, "fgpct": 0.0, "fouls": 0, "fta": 0, "ftm": 0, "ftpct": 0.0, "mins": 0, "offRebs": 0, "points": 0, "rebs": 0, "secs": 0, "steals": 0, "tpa": 0, "tpm": 0, "tppct": 0.0, "turnovers": 0}}, {"profile": {"teamProfile": {"abbr": "DET", "city": "\u5e95\u7279\u5f8b", "cityEn": "Detroit", "code": "pistons", "conference": "Eastern", "displayAbbr": "\u6d3b\u585e", "displayConference": "\u4e1c\u90e8", "division": "\u4e2d\u592e\u5206\u533a", "id": "1610612765", "isAllStarTeam": false, "isLeagueTeam": true, "leagueId": "00", "name": "\u6d3b\u585e", "nameEn": "Pistons"}, "oppTeamProfile": {"abbr": "PHI", "city": "\u8d39\u57ce", "cityEn": "Philadelphia", "code": "sixers", "conference": "Eastern", "displayAbbr": "76\u4eba", "displayConference": "\u4e1c\u90e8", "division": "\u5927\u897f\u6d0b\u5206\u533a", "id": "1610612755", "isAllStarTeam": false, "isLeagueTeam": true, "leagueId": "00", "name": "76\u4eba", "nameEn": "Sixers"}, "gameId": "0011900061", "isHome": "false", "oppTeamScore": 106, "teamScore": 86, "utcMillis": "1571180400000", "winOrLoss": "Lost"}, "statTotal": {"assists": 0, "blocks": 0, "defRebs": 0, "fga": 1, "fgm": 0, "fgpct": 0.0, "fouls": 0, "fta": 2, "ftm": 2, "ftpct": 100.0, "mins": 5, "offRebs": 0, "points": 2, "rebs": 0, "secs": 48, "steals": 0, "tpa": 1, "tpm": 0, "tppct": 0.0, "turnovers": 0}}, {"profile": {"teamProfile": {"abbr": "DET", "city": "\u5e95\u7279\u5f8b", "cityEn": "Detroit", "code": "pistons", "conference": "Eastern", "displayAbbr": "\u6d3b\u585e", "displayConference": "\u4e1c\u90e8", "division": "\u4e2d\u592e\u5206\u533a", "id": "1610612765", "isAllStarTeam": false, "isLeagueTeam": true, "leagueId": "00", "name": "\u6d3b\u585e", "nameEn": "Pistons"}, "oppTeamProfile": {"abbr": "CLE", "city": "\u514b\u5229\u592b\u5170", "cityEn": "Cleveland", "code": "cavaliers", "conference": "Eastern", "displayAbbr": "\u9a91\u58eb", "displayConference": "\u4e1c\u90e8", "division": "\u4e2d\u592e\u5206\u533a", "id": "1610612739", "isAllStarTeam": false, "isLeagueTeam": true, "leagueId": "00", "name": "\u9a91\u58eb", "nameEn": "Cavaliers"}, "gameId": "0011900037", "isHome": "true", "oppTeamScore": 105, "teamScore": 109, "utcMillis": "1570834800000", "winOrLoss": "Won"}, "statTotal": {"assists": 0, "blocks": 0, "defRebs": 0, "fga": 0, "fgm": 0, "fgpct": 0.0, "fouls": 0, "fta": 0, "ftm": 0, "ftpct": 0.0, "mins": 0, "offRebs": 0, "points": 0, "rebs": 0, "secs": 0, "steals": 0, "tpa": 0, "tpm": 0, "tppct": 0.0, "turnovers": 0}}, {"profile": {"teamProfile": {"abbr": "DET", "city": "\u5e95\u7279\u5f8b", "cityEn": "Detroit", "code": "pistons", "conference": "Eastern", "displayAbbr": "\u6d3b\u585e", "displayConference": "\u4e1c\u90e8", "division": "\u4e2d\u592e\u5206\u533a", "id": "1610612765", "isAllStarTeam": false, "isLeagueTeam": true, "leagueId": "00", "name": "\u6d3b\u585e", "nameEn": "Pistons"}, "oppTeamProfile": {"abbr": "DAL", "city": "\u8fbe\u62c9\u65af", "cityEn": "Dallas", "code": "mavericks", "conference": "Western", "displayAbbr": "\u72ec\u884c\u4fa0", "displayConference": "\u897f\u90e8", "division": "\u897f\u5357\u5206\u533a", "id": "1610612742", "isAllStarTeam": false, "isLeagueTeam": true, "leagueId": "00", "name": "\u72ec\u884c\u4fa0", "nameEn": "Mavericks"}, "gameId": "0011900024", "isHome": "true", "oppTeamScore": 117, "teamScore": 124, "utcMillis": "1570662000000", "winOrLoss": "Won"}, "statTotal": {"assists": 0, "blocks": 0, "defRebs": 0, "fga": 2, "fgm": 1, "fgpct": 50.0, "fouls": 0, "fta": 0, "ftm": 0, "ftpct": 0.0, "mins": 2, "offRebs": 0, "points": 3, "rebs": 0, "secs": 53, "steals": 0, "tpa": 1, "tpm": 1, "tppct": 100.0, "turnovers": 1}}, {"profile": {"teamProfile": {"abbr": "DET", "city": "\u5e95\u7279\u5f8b", "cityEn": "Detroit", "code": "pistons", "conference": "Eastern", "displayAbbr": "\u6d3b\u585e", "displayConference": "\u4e1c\u90e8", "division": "\u4e2d\u592e\u5206\u533a", "id": "1610612765", "isAllStarTeam": false, "isLeagueTeam": true, "leagueId": "00", "name": "\u6d3b\u585e", "nameEn": "Pistons"}, "oppTeamProfile": {"abbr": "ORL", "city": "\u5965\u5170\u591a", "cityEn": "Orlando", "code": "magic", "conference": "Eastern", "displayAbbr": "\u9b54\u672f", "displayConference": "\u4e1c\u90e8", "division": "\u4e1c\u5357\u5206\u533a", "id": "1610612753", "isAllStarTeam": false, "isLeagueTeam": true, "leagueId": "00", "name": "\u9b54\u672f", "nameEn": "Magic"}, "gameId": "0011900013", "isHome": "true", "oppTeamScore": 115, "teamScore": 91, "utcMillis": "1570489200000", "winOrLoss": "Lost"}, "statTotal": {"assists": 1, "blocks": 0, "defRebs": 0, "fga": 1, "fgm": 0, "fgpct": 0.0, "fouls": 0, "fta": 0, "ftm": 0, "ftpct": 0.0, "mins": 6, "offRebs": 0, "points": 0, "rebs": 0, "secs": 46, "steals": 0, "tpa": 0, "tpm": 0, "tppct": 0.0, "turnovers": 1}}, {"profile": {"teamProfile": {"abbr": "DET", "city": "\u5e95\u7279\u5f8b", "cityEn": "Detroit", "code": "pistons", "conference": "summer", "displayAbbr": "\u6d3b\u585e", "displayConference": "\u62c9\u65af\u7ef4\u52a0\u65af\u590f\u5b63", "division": "", "id": "1610612765", "isAllStarTeam": false, "isLeagueTeam": true, "leagueId": "15", "name": "\u6d3b\u585e", "nameEn": "Pistons"}, "oppTeamProfile": {"abbr": "BKN", "city": "\u5e03\u9c81\u514b\u6797", "cityEn": "Brooklyn", "code": "nets", "conference": "summer", "displayAbbr": "\u7bee\u7f51", "displayConference": "\u62c9\u65af\u7ef4\u52a0\u65af\u590f\u5b63", "division": "", "id": "1610612751", "isAllStarTeam": false, "isLeagueTeam": true, "leagueId": "15", "name": "\u7bee\u7f51", "nameEn": "Nets"}, "gameId": "1521900078", "isHome": "true", "oppTeamScore": 105, "teamScore": 85, "utcMillis": "1563064200000", "winOrLoss": "Lost"}, "statTotal": {"assists": 2, "blocks": 0, "defRebs": 4, "fga": 18, "fgm": 7, "fgpct": 38.9, "fouls": 4, "fta": 0, "ftm": 0, "ftpct": 0.0, "mins": 29, "offRebs": 1, "points": 15, "rebs": 5, "secs": 31, "steals": 1, "tpa": 6, "tpm": 1, "tppct": 16.7, "turnovers": 1}}, {"profile": {"teamProfile": {"abbr": "DET", "city": "\u5e95\u7279\u5f8b", "cityEn": "Detroit", "code": "pistons", "conference": "summer", "displayAbbr": "\u6d3b\u585e", "displayConference": "\u62c9\u65af\u7ef4\u52a0\u65af\u590f\u5b63", "division": "", "id": "1610612765", "isAllStarTeam": false, "isLeagueTeam": true, "leagueId": "15", "name": "\u6d3b\u585e", "nameEn": "Pistons"}, "oppTeamProfile": {"abbr": "PHI", "city": "\u8d39\u57ce", "cityEn": "Philadelphia", "code": "sixers", "conference": "summer", "displayAbbr": "76\u4eba", "displayConference": "\u62c9\u65af\u7ef4\u52a0\u65af\u590f\u5b63", "division": "", "id": "1610612755", "isAllStarTeam": false, "isLeagueTeam": true, "leagueId": "15", "name": "76\u4eba", "nameEn": "76ers"}, "gameId": "1521900049", "isHome": "true", "oppTeamScore": 81, "teamScore": 96, "utcMillis": "1562785200000", "winOrLoss": "Won"}, "statTotal": {"assists": 2, "blocks": 0, "defRebs": 4, "fga": 11, "fgm": 3, "fgpct": 27.3, "fouls": 1, "fta": 1, "ftm": 1, "ftpct": 100.0, "mins": 26, "offRebs": 0, "points": 7, "rebs": 4, "secs": 52, "steals": 2, "tpa": 3, "tpm": 0, "tppct": 0.0, "turnovers": 2}}, {"profile": {"teamProfile": {"abbr": "DET", "city": "\u5e95\u7279\u5f8b", "cityEn": "Detroit", "code": "pistons", "conference": "summer", "displayAbbr": "\u6d3b\u585e", "displayConference": "\u62c9\u65af\u7ef4\u52a0\u65af\u590f\u5b63", "division": "", "id": "1610612765", "isAllStarTeam": false, "isLeagueTeam": true, "leagueId": "15", "name": "\u6d3b\u585e", "nameEn": "Pistons"}, "oppTeamProfile": {"abbr": "IND", "city": "\u5370\u7b2c\u5b89\u7eb3", "cityEn": "Indiana", "code": "pacers", "conference": "summer", "displayAbbr": "\u6b65\u884c\u8005", "displayConference": "\u62c9\u65af\u7ef4\u52a0\u65af\u590f\u5b63", "division": "", "id": "1610612754", "isAllStarTeam": false, "isLeagueTeam": true, "leagueId": "15", "name": "\u6b65\u884c\u8005", "nameEn": "Pacers"}, "gameId": "1521900032", "isHome": "true", "oppTeamScore": 84, "teamScore": 102, "utcMillis": "1562619600000", "winOrLoss": "Won"}, "statTotal": {"assists": 3, "blocks": 0, "defRebs": 1, "fga": 9, "fgm": 4, "fgpct": 44.4, "fouls": 2, "fta": 0, "ftm": 0, "ftpct": 0.0, "mins": 26, "offRebs": 0, "points": 11, "rebs": 1, "secs": 46, "steals": 4, "tpa": 4, "tpm": 3, "tppct": 75.0, "turnovers": 2}}, {"profile": {"teamProfile": {"abbr": "DET", "city": "\u5e95\u7279\u5f8b", "cityEn": "Detroit", "code": "pistons", "conference": "summer", "displayAbbr": "\u6d3b\u585e", "displayConference": "\u62c9\u65af\u7ef4\u52a0\u65af\u590f\u5b63", "division": "", "id": "1610612765", "isAllStarTeam": false, "isLeagueTeam": true, "leagueId": "15", "name": "\u6d3b\u585e", "nameEn": "Pistons"}, "oppTeamProfile": {"abbr": "POR", "city": "\u6ce2\u7279\u5170", "cityEn": "Portland", "code": "blazers", "conference": "summer", "displayAbbr": "\u5f00\u62d3\u8005", "displayConference": "\u62c9\u65af\u7ef4\u52a0\u65af\u590f\u5b63", "division": "", "id": "1610612757", "isAllStarTeam": false, "isLeagueTeam": true, "leagueId": "15", "name": "\u5f00\u62d3\u8005", "nameEn": "Trail Blazers"}, "gameId": "1521900012", "isHome": "true", "oppTeamScore": 73, "teamScore": 93, "utcMillis": "1562441400000", "winOrLoss": "Won"}, "statTotal": {"assists": 2, "blocks": 0, "defRebs": 2, "fga": 14, "fgm": 3, "fgpct": 21.4, "fouls": 2, "fta": 0, "ftm": 0, "ftpct": 0.0, "mins": 25, "offRebs": 1, "points": 8, "rebs": 3, "secs": 25, "steals": 0, "tpa": 7, "tpm": 2, "tppct": 28.6, "turnovers": 1}}, {"profile": {"teamProfile": {"abbr": "DET", "city": "\u5e95\u7279\u5f8b", "cityEn": "Detroit", "code": "pistons", "conference": "summer", "displayAbbr": "\u6d3b\u585e", "displayConference": "\u62c9\u65af\u7ef4\u52a0\u65af\u590f\u5b63", "division": "", "id": "1610612765", "isAllStarTeam": false, "isLeagueTeam": true, "leagueId": "15", "name": "\u6d3b\u585e", "nameEn": "Pistons"}, "oppTeamProfile": {"abbr": "CRO", "city": "Croatia", "cityEn": "Croatia", "code": "croatia", "conference": "summer", "displayAbbr": "CRO", "displayConference": "\u62c9\u65af\u7ef4\u52a0\u65af\u590f\u5b63", "division": "", "id": "70", "isAllStarTeam": false, "isLeagueTeam": false, "leagueId": "15", "name": "Croatia", "nameEn": "Croatia"}, "gameId": "1521900001", "isHome": "false", "oppTeamScore": 80, "teamScore": 96, "utcMillis": "1562353200000", "winOrLoss": "Won"}, "statTotal": {"assists": 2, "blocks": 0, "defRebs": 5, "fga": 20, "fgm": 9, "fgpct": 45.0, "fouls": 2, "fta": 1, "ftm": 1, "ftpct": 100.0, "mins": 31, "offRebs": 1, "points": 26, "rebs": 6, "secs": 42, "steals": 2, "tpa": 14, "tpm": 7, "tppct": 50.0, "turnovers": 4}}], "regularSeasonCareerStat": {"statAverage": {"assistsPg": 0.3, "blocksPg": 0.1, "defRebsPg": 0.5, "efficiency": null, "fgaPg": 2.529, "fgmPg": 0.794, "fgpct": 31.4, "foulsPg": 0.9, "ftaPg": 0.441, "ftmPg": 0.265, "ftpct": 60.0, "games": 34, "gamesStarted": 0, "minsPg": 7.5, "offRebsPg": 0.1, "pointsPg": 2.3, "rebsPg": 0.6, "stealsPg": 0.29, "tpaPg": 1.441, "tpmPg": 0.441, "tppct": 30.6, "turnoversPg": 0.21}, "statTotal": {"assists": 11, "blocks": 5, "defRebs": 16, "fga": 86, "fgm": 27, "fgpct": 31.4, "fouls": 31, "fta": 15, "ftm": 9, "ftpct": 60.0, "mins": 257, "offRebs": 5, "points": 78, "rebs": 21, "secs": 0, "steals": 10, "tpa": 49, "tpm": 15, "tppct": 30.6, "turnovers": 7}}, "playoffCareerStat": {"statAverage": {"assistsPg": 0.0, "blocksPg": 0.0, "defRebsPg": 0.7, "efficiency": null, "fgaPg": 4.0, "fgmPg": 2.0, "fgpct": 50.0, "foulsPg": 0.0, "ftaPg": 0.333, "ftmPg": 0.333, "ftpct": 100.0, "games": 3, "gamesStarted": 0, "minsPg": 5.0, "offRebsPg": 0.0, "pointsPg": 4.7, "rebsPg": 0.7, "stealsPg": 0.67, "tpaPg": 1.333, "tpmPg": 0.333, "tppct": 25.0, "turnoversPg": 0.0}, "statTotal": {"assists": 0, "blocks": 0, "defRebs": 2, "fga": 12, "fgm": 6, "fgpct": 50.0, "fouls": 0, "fta": 1, "ftm": 1, "ftpct": 100.0, "mins": 15, "offRebs": 0, "points": 14, "rebs": 2, "secs": 0, "steals": 2, "tpa": 4, "tpm": 1, "tppct": 25.0, "turnovers": 0}}, "playerSplit": {"splits": [{"statAverage": {"assistsPg": 0.0, "blocksPg": 0.0, "defRebsPg": 0.0, "efficiency": null, "fgaPg": 0.5, "fgmPg": 0.0, "fgpct": 0.0, "foulsPg": null, "ftaPg": 1.0, "ftmPg": 0.5, "ftpct": 50.0, "games": 2, "gamesStarted": 0, "minsPg": 4.0, "offRebsPg": 0.0, "pointsPg": 0.5, "rebsPg": 0.0, "stealsPg": 0.5, "tpaPg": 0.5, "tpmPg": 0.0, "tppct": 0.0, "turnoversPg": null}, "statTotal": {"assists": 0, "blocks": 0, "defRebs": 0, "fga": 1, "fgm": 0, "fgpct": 0.0, "fouls": null, "fta": 2, "ftm": 1, "ftpct": 50.0, "mins": 0, "offRebs": 0, "points": 1, "rebs": 0, "secs": 0, "steals": 1, "tpa": 1, "tpm": 0, "tppct": 0.0, "turnovers": null}, "displayName": "\u4f11\u606f1\u5929", "name": "1 Days Rest"}, {"statAverage": {"assistsPg": 0.6, "blocksPg": 0.0, "defRebsPg": 0.0, "efficiency": null, "fgaPg": 2.0, "fgmPg": 0.667, "fgpct": 33.3, "foulsPg": null, "ftaPg": 0.667, "ftmPg": 0.333, "ftpct": 50.0, "games": 3, "gamesStarted": 0, "minsPg": 8.3, "offRebsPg": 0.0, "pointsPg": 2.3, "rebsPg": 0.0, "stealsPg": 0.6, "tpaPg": 2.0, "tpmPg": 0.667, "tppct": 33.3, "turnoversPg": null}, "statTotal": {"assists": 2, "blocks": 0, "defRebs": 0, "fga": 6, "fgm": 2, "fgpct": 33.3, "fouls": null, "fta": 2, "ftm": 1, "ftpct": 50.0, "mins": 0, "offRebs": 0, "points": 7, "rebs": 0, "secs": 0, "steals": 2, "tpa": 6, "tpm": 2, "tppct": 33.3, "turnovers": null}, "displayName": "\u4f11\u606f2\u5929", "name": "2 Days Rest"}, {"statAverage": {"assistsPg": 0.0, "blocksPg": 0.0, "defRebsPg": 0.0, "efficiency": null, "fgaPg": 6.0, "fgmPg": 2.0, "fgpct": 33.3, "foulsPg": null, "ftaPg": 0.0, "ftmPg": 0.0, "ftpct": 0.0, "games": 1, "gamesStarted": 0, "minsPg": 13.0, "offRebsPg": 1.0, "pointsPg": 6.0, "rebsPg": 1.0, "stealsPg": 0.0, "tpaPg": 4.0, "tpmPg": 2.0, "tppct": 50.0, "turnoversPg": null}, "statTotal": {"assists": 0, "blocks": 0, "defRebs": 0, "fga": 6, "fgm": 2, "fgpct": 33.3, "fouls": null, "fta": 0, "ftm": 0, "ftpct": 0.0, "mins": 0, "offRebs": 1, "points": 6, "rebs": 1, "secs": 0, "steals": 0, "tpa": 4, "tpm": 2, "tppct": 50.0, "turnovers": null}, "displayName": "\u4f11\u606f3\u5929", "name": "3 Days Rest"}, {"statAverage": {"assistsPg": 0.5, "blocksPg": 0.0, "defRebsPg": 0.0, "efficiency": null, "fgaPg": 2.0, "fgmPg": 0.5, "fgpct": 25.0, "foulsPg": null, "ftaPg": 0.0, "ftmPg": 0.0, "ftpct": 0.0, "games": 2, "gamesStarted": 0, "minsPg": 8.0, "offRebsPg": 0.0, "pointsPg": 1.5, "rebsPg": 0.0, "stealsPg": 0.0, "tpaPg": 1.5, "tpmPg": 0.5, "tppct": 33.3, "turnoversPg": null}, "statTotal": {"assists": 1, "blocks": 0, "defRebs": 0, "fga": 4, "fgm": 1, "fgpct": 25.0, "fouls": null, "fta": 0, "ftm": 0, "ftpct": 0.0, "mins": 0, "offRebs": 0, "points": 3, "rebs": 0, "secs": 0, "steals": 0, "tpa": 3, "tpm": 1, "tppct": 33.3, "turnovers": null}, "displayName": "\u4f11\u606f3+\u5929", "name": "3+ Days Rest"}, {"statAverage": {"assistsPg": 1.0, "blocksPg": 0.0, "defRebsPg": 0.0, "efficiency": null, "fgaPg": 4.0, "fgmPg": 1.0, "fgpct": 25.0, "foulsPg": null, "ftaPg": 0.0, "ftmPg": 0.0, "ftpct": 0.0, "games": 1, "gamesStarted": 0, "minsPg": 14.0, "offRebsPg": 0.0, "pointsPg": 3.0, "rebsPg": 0.0, "stealsPg": 0.0, "tpaPg": 3.0, "tpmPg": 1.0, "tppct": 33.3, "turnoversPg": null}, "statTotal": {"assists": 1, "blocks": 0, "defRebs": 0, "fga": 4, "fgm": 1, "fgpct": 25.0, "fouls": null, "fta": 0, "ftm": 0, "ftpct": 0.0, "mins": 0, "offRebs": 0, "points": 3, "rebs": 0, "secs": 0, "steals": 0, "tpa": 3, "tpm": 1, "tppct": 33.3, "turnovers": null}, "displayName": "\u5bf9\u9635 \u6398\u91d1", "name": "Against Den"}, {"statAverage": {"assistsPg": 0.0, "blocksPg": 0.0, "defRebsPg": 0.0, "efficiency": null, "fgaPg": 3.0, "fgmPg": 1.0, "fgpct": 33.3, "foulsPg": null, "ftaPg": 1.0, "ftmPg": 0.5, "ftpct": 50.0, "games": 2, "gamesStarted": 0, "minsPg": 8.5, "offRebsPg": 0.5, "pointsPg": 3.5, "rebsPg": 0.5, "stealsPg": 0.0, "tpaPg": 2.0, "tpmPg": 1.0, "tppct": 50.0, "turnoversPg": null}, "statTotal": {"assists": 0, "blocks": 0, "defRebs": 0, "fga": 6, "fgm": 2, "fgpct": 33.3, "fouls": null, "fta": 2, "ftm": 1, "ftpct": 50.0, "mins": 0, "offRebs": 1, "points": 7, "rebs": 1, "secs": 0, "steals": 0, "tpa": 4, "tpm": 2, "tppct": 50.0, "turnovers": null}, "displayName": "\u5bf9\u9635 \u5c3c\u514b\u65af", "name": "Against NY"}, {"statAverage": {"assistsPg": 1.0, "blocksPg": 0.0, "defRebsPg": 0.0, "efficiency": null, "fgaPg": 2.0, "fgmPg": 0.0, "fgpct": 0.0, "foulsPg": null, "ftaPg": 0.0, "ftmPg": 0.0, "ftpct": 0.0, "games": 1, "gamesStarted": 0, "minsPg": 9.0, "offRebsPg": 0.0, "pointsPg": 0.0, "rebsPg": 0.0, "stealsPg": 1.0, "tpaPg": 2.0, "tpmPg": 0.0, "tppct": 0.0, "turnoversPg": null}, "statTotal": {"assists": 1, "blocks": 0, "defRebs": 0, "fga": 2, "fgm": 0, "fgpct": 0.0, "fouls": null, "fta": 0, "ftm": 0, "ftpct": 0.0, "mins": 0, "offRebs": 0, "points": 0, "rebs": 0, "secs": 0, "steals": 1, "tpa": 2, "tpm": 0, "tppct": 0.0, "turnovers": null}, "displayName": "\u5bf9\u9635 OKC", "name": "Against OKC"}, {"statAverage": {"assistsPg": 1.0, "blocksPg": 0.0, "defRebsPg": 0.0, "efficiency": null, "fgaPg": 3.0, "fgmPg": 1.0, "fgpct": 33.3, "foulsPg": null, "ftaPg": 2.0, "ftmPg": 1.0, "ftpct": 50.0, "games": 1, "gamesStarted": 0, "minsPg": 14.0, "offRebsPg": 0.0, "pointsPg": 4.0, "rebsPg": 0.0, "stealsPg": 1.0, "tpaPg": 3.0, "tpmPg": 1.0, "tppct": 33.3, "turnoversPg": null}, "statTotal": {"assists": 1, "blocks": 0, "defRebs": 0, "fga": 3, "fgm": 1, "fgpct": 33.3, "fouls": null, "fta": 2, "ftm": 1, "ftpct": 50.0, "mins": 0, "offRebs": 0, "points": 4, "rebs": 0, "secs": 0, "steals": 1, "tpa": 3, "tpm": 1, "tppct": 33.3, "turnovers": null}, "displayName": "\u5bf9\u9635 76\u4eba", "name": "Against Phi"}, {"statAverage": {"assistsPg": 0.0, "blocksPg": 0.0, "defRebsPg": 0.0, "efficiency": null, "fgaPg": 1.0, "fgmPg": 1.0, "fgpct": 100.0, "foulsPg": null, "ftaPg": 0.0, "ftmPg": 0.0, "ftpct": 0.0, "games": 1, "gamesStarted": 0, "minsPg": 2.0, "offRebsPg": 0.0, "pointsPg": 3.0, "rebsPg": 0.0, "stealsPg": 0.0, "tpaPg": 1.0, "tpmPg": 1.0, "tppct": 100.0, "turnoversPg": null}, "statTotal": {"assists": 0, "blocks": 0, "defRebs": 0, "fga": 1, "fgm": 1, "fgpct": 100.0, "fouls": null, "fta": 0, "ftm": 0, "ftpct": 0.0, "mins": 0, "offRebs": 0, "points": 3, "rebs": 0, "secs": 0, "steals": 0, "tpa": 1, "tpm": 1, "tppct": 100.0, "turnovers": null}, "displayName": "\u5bf9\u9635 \u592a\u9633", "name": "Against Pho"}, {"statAverage": {"assistsPg": 0.0, "blocksPg": 0.0, "defRebsPg": 0.0, "efficiency": null, "fgaPg": 1.0, "fgmPg": 0.0, "fgpct": 0.0, "foulsPg": null, "ftaPg": 0.0, "ftmPg": 0.0, "ftpct": 0.0, "games": 1, "gamesStarted": 0, "minsPg": 4.0, "offRebsPg": 0.0, "pointsPg": 0.0, "rebsPg": 0.0, "stealsPg": 1.0, "tpaPg": 1.0, "tpmPg": 0.0, "tppct": 0.0, "turnoversPg": null}, "statTotal": {"assists": 0, "blocks": 0, "defRebs": 0, "fga": 1, "fgm": 0, "fgpct": 0.0, "fouls": null, "fta": 0, "ftm": 0, "ftpct": 0.0, "mins": 0, "offRebs": 0, "points": 0, "rebs": 0, "secs": 0, "steals": 1, "tpa": 1, "tpm": 0, "tppct": 0.0, "turnovers": null}, "displayName": "\u5bf9\u9635 \u56fd\u738b", "name": "Against Sac"}, {"statAverage": {"assistsPg": 0.0, "blocksPg": 0.0, "defRebsPg": 0.0, "efficiency": null, "fgaPg": 0.0, "fgmPg": 0.0, "fgpct": 0.0, "foulsPg": null, "ftaPg": 0.0, "ftmPg": 0.0, "ftpct": 0.0, "games": 1, "gamesStarted": 0, "minsPg": 2.0, "offRebsPg": 0.0, "pointsPg": 0.0, "rebsPg": 0.0, "stealsPg": 0.0, "tpaPg": 0.0, "tpmPg": 0.0, "tppct": 0.0, "turnoversPg": null}, "statTotal": {"assists": 0, "blocks": 0, "defRebs": 0, "fga": 0, "fgm": 0, "fgpct": 0.0, "fouls": null, "fta": 0, "ftm": 0, "ftpct": 0.0, "mins": 0, "offRebs": 0, "points": 0, "rebs": 0, "secs": 0, "steals": 0, "tpa": 0, "tpm": 0, "tppct": 0.0, "turnovers": null}, "displayName": "\u5bf9\u9635 \u5947\u624d", "name": "Against Was"}, {"statAverage": {"assistsPg": 0.2, "blocksPg": 0.0, "defRebsPg": 0.0, "efficiency": null, "fgaPg": 2.25, "fgmPg": 0.75, "fgpct": 33.3, "foulsPg": null, "ftaPg": 1.0, "ftmPg": 0.5, "ftpct": 50.0, "games": 4, "gamesStarted": 0, "minsPg": 8.2, "offRebsPg": 0.2, "pointsPg": 2.7, "rebsPg": 0.2, "stealsPg": 0.2, "tpaPg": 1.75, "tpmPg": 0.75, "tppct": 42.9, "turnoversPg": null}, "statTotal": {"assists": 1, "blocks": 0, "defRebs": 0, "fga": 9, "fgm": 3, "fgpct": 33.3, "fouls": null, "fta": 4, "ftm": 2, "ftpct": 50.0, "mins": 0, "offRebs": 1, "points": 11, "rebs": 1, "secs": 0, "steals": 1, "tpa": 7, "tpm": 3, "tppct": 42.9, "turnovers": null}, "displayName": "\u8054\u76df", "name": "Conference"}, {"statAverage": {"assistsPg": 0.5, "blocksPg": 0.0, "defRebsPg": 0.0, "efficiency": null, "fgaPg": 2.5, "fgmPg": 1.0, "fgpct": 40.0, "foulsPg": null, "ftaPg": 0.0, "ftmPg": 0.0, "ftpct": 0.0, "games": 2, "gamesStarted": 0, "minsPg": 8.0, "offRebsPg": 0.0, "pointsPg": 3.0, "rebsPg": 0.0, "stealsPg": 0.0, "tpaPg": 2.0, "tpmPg": 1.0, "tppct": 50.0, "turnoversPg": null}, "statTotal": {"assists": 1, "blocks": 0, "defRebs": 0, "fga": 5, "fgm": 2, "fgpct": 40.0, "fouls": null, "fta": 0, "ftm": 0, "ftpct": 0.0, "mins": 0, "offRebs": 0, "points": 6, "rebs": 0, "secs": 0, "steals": 0, "tpa": 4, "tpm": 2, "tppct": 50.0, "turnovers": null}, "displayName": "\u4e8c\u6708", "name": "February"}, {"statAverage": {"assistsPg": 0.5, "blocksPg": 0.0, "defRebsPg": 0.0, "efficiency": null, "fgaPg": 2.667, "fgmPg": 0.667, "fgpct": 25.0, "foulsPg": null, "ftaPg": 0.333, "ftmPg": 0.167, "ftpct": 50.0, "games": 6, "gamesStarted": 0, "minsPg": 9.1, "offRebsPg": 0.1, "pointsPg": 2.1, "rebsPg": 0.1, "stealsPg": 0.5, "tpaPg": 2.167, "tpmPg": 0.667, "tppct": 30.8, "turnoversPg": null}, "statTotal": {"assists": 3, "blocks": 0, "defRebs": 0, "fga": 16, "fgm": 4, "fgpct": 25.0, "fouls": null, "fta": 2, "ftm": 1, "ftpct": 50.0, "mins": 0, "offRebs": 1, "points": 13, "rebs": 1, "secs": 0, "steals": 3, "tpa": 13, "tpm": 4, "tppct": 30.8, "turnovers": null}, "displayName": "\u8d1f", "name": "Games Lost"}, {"statAverage": {"assistsPg": 0.0, "blocksPg": 0.0, "defRebsPg": 0.0, "efficiency": null, "fgaPg": 0.5, "fgmPg": 0.5, "fgpct": 100.0, "foulsPg": null, "ftaPg": 1.0, "ftmPg": 0.5, "ftpct": 50.0, "games": 2, "gamesStarted": 0, "minsPg": 3.0, "offRebsPg": 0.0, "pointsPg": 2.0, "rebsPg": 0.0, "stealsPg": 0.0, "tpaPg": 0.5, "tpmPg": 0.5, "tppct": 100.0, "turnoversPg": null}, "statTotal": {"assists": 0, "blocks": 0, "defRebs": 0, "fga": 1, "fgm": 1, "fgpct": 100.0, "fouls": null, "fta": 2, "ftm": 1, "ftpct": 50.0, "mins": 0, "offRebs": 0, "points": 4, "rebs": 0, "secs": 0, "steals": 0, "tpa": 1, "tpm": 1, "tppct": 100.0, "turnovers": null}, "displayName": "\u80dc", "name": "Games Won"}, {"statAverage": {"assistsPg": 0.5, "blocksPg": 0.0, "defRebsPg": 0.0, "efficiency": null, "fgaPg": 1.0, "fgmPg": 0.0, "fgpct": 0.0, "foulsPg": null, "ftaPg": 1.0, "ftmPg": 0.5, "ftpct": 50.0, "games": 2, "gamesStarted": 0, "minsPg": 6.0, "offRebsPg": 0.0, "pointsPg": 0.5, "rebsPg": 0.0, "stealsPg": 0.5, "tpaPg": 1.0, "tpmPg": 0.0, "tppct": 0.0, "turnoversPg": null}, "statTotal": {"assists": 1, "blocks": 0, "defRebs": 0, "fga": 2, "fgm": 0, "fgpct": 0.0, "fouls": null, "fta": 2, "ftm": 1, "ftpct": 50.0, "mins": 0, "offRebs": 0, "points": 1, "rebs": 0, "secs": 0, "steals": 1, "tpa": 2, "tpm": 0, "tppct": 0.0, "turnovers": null}, "displayName": "\u4e3b\u573a", "name": "Home"}, {"statAverage": {"assistsPg": 0.3, "blocksPg": 0.0, "defRebsPg": 0.0, "efficiency": null, "fgaPg": 2.125, "fgmPg": 0.625, "fgpct": 29.4, "foulsPg": null, "ftaPg": 0.5, "ftmPg": 0.25, "ftpct": 50.0, "games": 8, "gamesStarted": 0, "minsPg": 7.6, "offRebsPg": 0.1, "pointsPg": 2.1, "rebsPg": 0.1, "stealsPg": 0.3, "tpaPg": 1.75, "tpmPg": 0.625, "tppct": 35.7, "turnoversPg": null}, "statTotal": {"assists": 3, "blocks": 0, "defRebs": 0, "fga": 17, "fgm": 5, "fgpct": 29.4, "fouls": null, "fta": 4, "ftm": 2, "ftpct": 50.0, "mins": 0, "offRebs": 1, "points": 17, "rebs": 1, "secs": 0, "steals": 3, "tpa": 14, "tpm": 5, "tppct": 35.7, "turnovers": null}, "displayName": "\u6700\u8fd1\u5341\u573a\u6bd4\u8d5b", "name": "Last 10 Games"}, {"statAverage": {"assistsPg": 0.4, "blocksPg": 0.0, "defRebsPg": 0.0, "efficiency": null, "fgaPg": 2.6, "fgmPg": 0.8, "fgpct": 30.8, "foulsPg": 1.4, "ftaPg": 0.4, "ftmPg": 0.2, "ftpct": 50.0, "games": 5, "gamesStarted": 0, "minsPg": 8.4, "offRebsPg": 0.2, "pointsPg": 2.6, "rebsPg": 0.2, "stealsPg": 0.6, "tpaPg": 2.2, "tpmPg": 0.8, "tppct": 36.4, "turnoversPg": 0.4}, "statTotal": {"assists": 2, "blocks": 0, "defRebs": 0, "fga": 13, "fgm": 4, "fgpct": 30.8, "fouls": 7, "fta": 2, "ftm": 1, "ftpct": 50.0, "mins": 0, "offRebs": 1, "points": 13, "rebs": 1, "secs": 0, "steals": 3, "tpa": 11, "tpm": 4, "tppct": 36.4, "turnovers": 2}, "displayName": "\u6700\u8fd1\u4e94\u573a\u6bd4\u8d5b", "name": "Last 5 Games"}, {"statAverage": {"assistsPg": 0.5, "blocksPg": 0.0, "defRebsPg": 0.0, "efficiency": null, "fgaPg": 3.0, "fgmPg": 0.75, "fgpct": 25.0, "foulsPg": null, "ftaPg": 0.5, "ftmPg": 0.25, "ftpct": 50.0, "games": 4, "gamesStarted": 0, "minsPg": 10.0, "offRebsPg": 0.2, "pointsPg": 2.5, "rebsPg": 0.2, "stealsPg": 0.7, "tpaPg": 2.5, "tpmPg": 0.75, "tppct": 30.0, "turnoversPg": null}, "statTotal": {"assists": 2, "blocks": 0, "defRebs": 0, "fga": 12, "fgm": 3, "fgpct": 25.0, "fouls": null, "fta": 2, "ftm": 1, "ftpct": 50.0, "mins": 0, "offRebs": 1, "points": 10, "rebs": 1, "secs": 0, "steals": 3, "tpa": 10, "tpm": 3, "tppct": 30.0, "turnovers": null}, "displayName": "\u4e09\u6708", "name": "March"}, {"statAverage": {"assistsPg": 0.0, "blocksPg": 0.0, "defRebsPg": 0.0, "efficiency": null, "fgaPg": 0.0, "fgmPg": 0.0, "fgpct": 0.0, "foulsPg": null, "ftaPg": 1.0, "ftmPg": 0.5, "ftpct": 50.0, "games": 2, "gamesStarted": 0, "minsPg": 3.0, "offRebsPg": 0.0, "pointsPg": 0.5, "rebsPg": 0.0, "stealsPg": 0.0, "tpaPg": 0.0, "tpmPg": 0.0, "tppct": 0.0, "turnoversPg": null}, "statTotal": {"assists": 0, "blocks": 0, "defRebs": 0, "fga": 0, "fgm": 0, "fgpct": 0.0, "fouls": null, "fta": 2, "ftm": 1, "ftpct": 50.0, "mins": 0, "offRebs": 0, "points": 1, "rebs": 0, "secs": 0, "steals": 0, "tpa": 0, "tpm": 0, "tppct": 0.0, "turnovers": null}, "displayName": "\u5341\u4e00\u6708", "name": "November"}, {"statAverage": {"assistsPg": 0.3, "blocksPg": 0.0, "defRebsPg": 0.0, "efficiency": null, "fgaPg": 2.5, "fgmPg": 0.833, "fgpct": 33.3, "foulsPg": null, "ftaPg": 0.333, "ftmPg": 0.167, "ftpct": 50.0, "games": 6, "gamesStarted": 0, "minsPg": 8.1, "offRebsPg": 0.1, "pointsPg": 2.6, "rebsPg": 0.1, "stealsPg": 0.3, "tpaPg": 2.0, "tpmPg": 0.833, "tppct": 41.7, "turnoversPg": null}, "statTotal": {"assists": 2, "blocks": 0, "defRebs": 0, "fga": 15, "fgm": 5, "fgpct": 33.3, "fouls": null, "fta": 2, "ftm": 1, "ftpct": 50.0, "mins": 0, "offRebs": 1, "points": 16, "rebs": 1, "secs": 0, "steals": 2, "tpa": 12, "tpm": 5, "tppct": 41.7, "turnovers": null}, "displayName": "\u5ba2\u573a", "name": "Road"}], "last5Games": {"statAverage": {"assistsPg": 0.4, "blocksPg": 0.0, "defRebsPg": 0.0, "efficiency": null, "fgaPg": 2.4, "fgmPg": 0.6, "fgpct": 25.0, "foulsPg": 1.4, "ftaPg": 0.4, "ftmPg": 0.2, "ftpct": 50.0, "games": 5, "gamesStarted": 0, "minsPg": 8.0, "offRebsPg": 0.2, "pointsPg": 2.0, "rebsPg": 0.2, "stealsPg": 0.6, "tpaPg": 2.0, "tpmPg": 0.6, "tppct": 30.0, "turnoversPg": 0.4}, "statTotal": {"assists": 2, "blocks": 0, "defRebs": 0, "fga": 12, "fgm": 3, "fgpct": 25.0, "fouls": 7, "fta": 2, "ftm": 1, "ftpct": 50.0, "mins": 40, "offRebs": 1, "points": 10, "rebs": 1, "secs": 163, "steals": 3, "tpa": 10, "tpm": 3, "tppct": 30.0, "turnovers": 2}}}}}}, "timestamp": "1586883869743"}