{"context": {"user": {"countryCode": "CN", "countryName": "China", "locale": "zh_CN", "timeZone": "+08:00", "timeZoneCity": "Australia/Perth"}, "device": {"clazz": null}}, "error": {"detail": null, "isError": "false", "message": null}, "payload": {"league": {"id": "00", "name": "NBA"}, "season": {"isCurrent": "true", "rosterSeasonType": 2, "rosterSeasonYear": "2019", "rosterSeasonYearDisplay": "2019-2020", "scheduleSeasonType": 2, "scheduleSeasonYear": "2019", "scheduleYearDisplay": "2019-2020", "statsSeasonType": 2, "statsSeasonYear": "2019", "statsSeasonYearDisplay": "2019-2020", "year": "2019", "yearDisplay": "2019-2020"}, "leagueSeasonAverage": {"assistsPg": 2.303, "blocksPg": 0.469, "defRebsPg": 3.29, "efficiency": 5.435, "fgaPg": 8.4, "fgmPg": 3.85, "fgpct": 46.0, "foulsPg": 1.95, "ftaPg": 2.15, "ftmPg": 1.65, "ftpct": 77.1, "games": 20, "gamesStarted": null, "minsPg": 22.876, "offRebsPg": 0.959, "pointsPg": 10.545, "rebsPg": 4.248, "stealsPg": 0.724, "tpaPg": 3.2, "tpmPg": 1.15, "tppct": 35.7, "turnoversPg": 1.314}, "player": {"playerProfile": {"code": "kyrie_irving", "country": "\u6fb3\u6d32", "countryEn": "Australia", "displayAffiliation": "Duke/Australia", "displayName": "\u51ef\u91cc \u6b27\u6587", "displayNameEn": "Kyrie Irving", "dob": "701326800000", "draftYear": "2011", "experience": "8", "firstInitial": "\u51ef\u91cc", "firstName": "\u51ef\u91cc", "firstNameEn": "Kyrie", "height": "1.88", "jerseyNo": "11", "lastName": "\u6b27\u6587", "lastNameEn": "Irving", "leagueId": "00", "playerId": "202681", "position": "\u540e\u536b", "schoolType": "College", "weight": "88.5 \u516c\u65a4"}, "teamProfile": {"abbr": "BKN", "city": "\u5e03\u9c81\u514b\u6797", "cityEn": "Brooklyn", "code": "nets", "conference": "Eastern", "displayAbbr": "\u7bee\u7f51", "displayConference": "\u4e1c\u90e8", "division": "\u5927\u897f\u6d0b\u5206\u533a", "id": "1610612751", "isAllStarTeam": false, "isLeagueTeam": true, "leagueId": "00", "name": "\u7bee\u7f51", "nameEn": "Nets"}, "stats": {"currentSeasonTypeStat": {"season": {"type": "2", "typeDisplay": "\u5e38\u89c4\u8d5b", "year": "2019", "yearDisplay": "2019-2020"}, "currentSeasonTypePlayerTeamStats": [{"profile": {"abbr": "BOS", "city": "\u6ce2\u58eb\u987f", "cityEn": "Boston", "code": "celtics", "conference": "Eastern", "displayAbbr": "\u51ef\u5c14\u7279\u4eba", "displayConference": "\u4e1c\u90e8", "division": "\u5927\u897f\u6d0b\u5206\u533a", "id": "1610612738", "isAllStarTeam": false, "isLeagueTeam": true, "leagueId": "00", "name": "\u51ef\u5c14\u7279\u4eba", "nameEn": "Celtics"}, "statAverage": {"assistsPg": 0.0, "blocksPg": 0.0, "defRebsPg": 0.0, "efficiency": 0.0, "fgaPg": 0.0, "fgmPg": 0.0, "fgpct": 0.0, "foulsPg": 0.0, "ftaPg": 0.0, "ftmPg": 0.0, "ftpct": 0.0, "games": 0, "gamesStarted": 0, "minsPg": 0.0, "offRebsPg": 0.0, "pointsPg": 0.0, "rebsPg": 0.0, "stealsPg": 0.0, "tpaPg": 0.0, "tpmPg": 0.0, "tppct": 0.0, "turnoversPg": 0.0}, "statTotal": {"assists": 0, "blocks": 0, "defRebs": 0, "fga": 0, "fgm": 0, "fgpct": 0.0, "fouls": 0, "fta": 0, "ftm": 0, "ftpct": 0.0, "mins": 0, "offRebs": 0, "points": 0, "rebs": 0, "secs": 0, "steals": 0, "tpa": 0, "tpm": 0, "tppct": 0.0, "turnovers": 0}, "round": null, "roundText": null}, {"profile": {"abbr": "BKN", "city": "\u5e03\u9c81\u514b\u6797", "cityEn": "Brooklyn", "code": "nets", "conference": "Eastern", "displayAbbr": "\u7bee\u7f51", "displayConference": "\u4e1c\u90e8", "division": "\u5927\u897f\u6d0b\u5206\u533a", "id": "1610612751", "isAllStarTeam": false, "isLeagueTeam": true, "leagueId": "00", "name": "\u7bee\u7f51", "nameEn": "Nets"}, "statAverage": {"assistsPg": 6.4, "blocksPg": 0.5, "defRebsPg": 4.1, "efficiency": 27.0, "fgaPg": 20.8, "fgmPg": 9.95, "fgpct": 47.8, "foulsPg": 2.7, "ftaPg": 5.1, "ftmPg": 4.7, "ftpct": 92.2, "games": 20, "gamesStarted": 20, "minsPg": 32.9, "offRebsPg": 1.1, "pointsPg": 27.4, "rebsPg": 5.2, "stealsPg": 1.3, "tpaPg": 7.1, "tpmPg": 2.8, "tppct": 39.4, "turnoversPg": 2.6}, "statTotal": {"assists": 128, "blocks": 10, "defRebs": 81, "fga": 416, "fgm": 199, "fgpct": 47.8, "fouls": 53, "fta": 102, "ftm": 94, "ftpct": 92.2, "mins": 658, "offRebs": 22, "points": 548, "rebs": 103, "secs": 0, "steals": 27, "tpa": 142, "tpm": 56, "tppct": 39.4, "turnovers": 52}, "round": null, "roundText": null}, {"profile": null, "statAverage": {"assistsPg": 6.4, "blocksPg": 0.5, "defRebsPg": 4.1, "efficiency": 27.0, "fgaPg": 20.8, "fgmPg": 9.95, "fgpct": 47.8, "foulsPg": 2.7, "ftaPg": 5.1, "ftmPg": 4.7, "ftpct": 92.2, "games": 20, "gamesStarted": 20, "minsPg": 32.9, "offRebsPg": 1.1, "pointsPg": 27.4, "rebsPg": 5.2, "stealsPg": 1.4, "tpaPg": 7.1, "tpmPg": 2.8, "tppct": 39.4, "turnoversPg": 2.6}, "statTotal": {"assists": 128, "blocks": 10, "defRebs": 81, "fga": 416, "fgm": 199, "fgpct": 47.8, "fouls": 53, "fta": 102, "ftm": 94, "ftpct": 92.2, "mins": 658, "offRebs": 22, "points": 548, "rebs": 103, "secs": 0, "steals": 27, "tpa": 142, "tpm": 56, "tppct": 39.4, "turnovers": 52}, "round": null, "roundText": null}]}, "regularSeasonStat": {"playerTeams": [{"profile": {"abbr": "CLE", "city": "\u514b\u5229\u592b\u5170", "cityEn": "Cleveland", "code": "cavaliers", "conference": "Eastern", "displayAbbr": "\u9a91\u58eb", "displayConference": "\u4e1c\u90e8", "division": "\u4e2d\u592e\u5206\u533a", "id": "1610612739", "isAllStarTeam": false, "isLeagueTeam": true, "leagueId": "00", "name": "\u9a91\u58eb", "nameEn": "Cavaliers"}, "statAverage": {"assistsPg": 5.4, "blocksPg": 0.3, "defRebsPg": 2.9, "efficiency": 17.686, "fgaPg": 14.647, "fgmPg": 6.863, "fgpct": 46.9, "foulsPg": 2.2, "ftaPg": 3.843, "ftmPg": 3.353, "ftpct": 87.2, "games": 51, "gamesStarted": 51, "minsPg": 30.5, "offRebsPg": 0.9, "pointsPg": 18.5, "rebsPg": 3.8, "stealsPg": 1.0, "tpaPg": 3.588, "tpmPg": 1.431, "tppct": 39.9, "turnoversPg": 3.1}, "statTotal": {"assists": 275, "blocks": 20, "defRebs": 147, "fga": 747, "fgm": 350, "fgpct": 46.9, "fouls": 110, "fta": 196, "ftm": 171, "ftpct": 87.2, "mins": 1558, "offRebs": 44, "points": 944, "rebs": 191, "secs": 0, "steals": 54, "tpa": 183, "tpm": 73, "tppct": 39.9, "turnovers": 160}, "season": "2011"}, {"profile": {"abbr": "CLE", "city": "\u514b\u5229\u592b\u5170", "cityEn": "Cleveland", "code": "cavaliers", "conference": "Eastern", "displayAbbr": "\u9a91\u58eb", "displayConference": "\u4e1c\u90e8", "division": "\u4e2d\u592e\u5206\u533a", "id": "1610612739", "isAllStarTeam": false, "isLeagueTeam": true, "leagueId": "00", "name": "\u9a91\u58eb", "nameEn": "Cavaliers"}, "statAverage": {"assistsPg": 5.9, "blocksPg": 0.3, "defRebsPg": 3.1, "efficiency": 20.0, "fgaPg": 18.136, "fgmPg": 8.203, "fgpct": 45.2, "foulsPg": 2.5, "ftaPg": 4.915, "ftmPg": 4.203, "ftpct": 85.5, "games": 59, "gamesStarted": 59, "minsPg": 34.7, "offRebsPg": 0.6, "pointsPg": 22.5, "rebsPg": 3.7, "stealsPg": 1.5, "tpaPg": 4.729, "tpmPg": 1.847, "tppct": 39.1, "turnoversPg": 3.2}, "statTotal": {"assists": 350, "blocks": 21, "defRebs": 182, "fga": 1070, "fgm": 484, "fgpct": 45.2, "fouls": 146, "fta": 290, "ftm": 248, "ftpct": 85.5, "mins": 2048, "offRebs": 34, "points": 1325, "rebs": 216, "secs": 0, "steals": 89, "tpa": 279, "tpm": 109, "tppct": 39.1, "turnovers": 191}, "season": "2012"}, {"profile": {"abbr": "CLE", "city": "\u514b\u5229\u592b\u5170", "cityEn": "Cleveland", "code": "cavaliers", "conference": "Eastern", "displayAbbr": "\u9a91\u58eb", "displayConference": "\u4e1c\u90e8", "division": "\u4e2d\u592e\u5206\u533a", "id": "1610612739", "isAllStarTeam": false, "isLeagueTeam": true, "leagueId": "00", "name": "\u9a91\u58eb", "nameEn": "Cavaliers"}, "statAverage": {"assistsPg": 6.1, "blocksPg": 0.3, "defRebsPg": 2.9, "efficiency": 19.1, "fgaPg": 17.423, "fgmPg": 7.493, "fgpct": 43.0, "foulsPg": 2.3, "ftaPg": 4.761, "ftmPg": 4.099, "ftpct": 86.1, "games": 71, "gamesStarted": 71, "minsPg": 35.2, "offRebsPg": 0.7, "pointsPg": 20.8, "rebsPg": 3.6, "stealsPg": 1.5, "tpaPg": 4.845, "tpmPg": 1.732, "tppct": 35.8, "turnoversPg": 2.6}, "statTotal": {"assists": 433, "blocks": 23, "defRebs": 207, "fga": 1237, "fgm": 532, "fgpct": 43.0, "fouls": 163, "fta": 338, "ftm": 291, "ftpct": 86.1, "mins": 2496, "offRebs": 52, "points": 1478, "rebs": 259, "secs": 0, "steals": 108, "tpa": 344, "tpm": 123, "tppct": 35.8, "turnovers": 190}, "season": "2013"}, {"profile": {"abbr": "CLE", "city": "\u514b\u5229\u592b\u5170", "cityEn": "Cleveland", "code": "cavaliers", "conference": "Eastern", "displayAbbr": "\u9a91\u58eb", "displayConference": "\u4e1c\u90e8", "division": "\u4e2d\u592e\u5206\u533a", "id": "1610612739", "isAllStarTeam": false, "isLeagueTeam": true, "leagueId": "00", "name": "\u9a91\u58eb", "nameEn": "Cavaliers"}, "statAverage": {"assistsPg": 5.2, "blocksPg": 0.2, "defRebsPg": 2.4, "efficiency": 19.9, "fgaPg": 16.467, "fgmPg": 7.707, "fgpct": 46.8, "foulsPg": 1.9, "ftaPg": 4.867, "ftmPg": 4.2, "ftpct": 86.3, "games": 75, "gamesStarted": 75, "minsPg": 36.4, "offRebsPg": 0.7, "pointsPg": 21.7, "rebsPg": 3.1, "stealsPg": 1.5, "tpaPg": 5.04, "tpmPg": 2.093, "tppct": 41.5, "turnoversPg": 2.4}, "statTotal": {"assists": 389, "blocks": 20, "defRebs": 182, "fga": 1235, "fgm": 578, "fgpct": 46.8, "fouls": 146, "fta": 365, "ftm": 315, "ftpct": 86.3, "mins": 2730, "offRebs": 55, "points": 1628, "rebs": 237, "secs": 0, "steals": 114, "tpa": 378, "tpm": 157, "tppct": 41.5, "turnovers": 186}, "season": "2014"}, {"profile": {"abbr": "CLE", "city": "\u514b\u5229\u592b\u5170", "cityEn": "Cleveland", "code": "cavaliers", "conference": "Eastern", "displayAbbr": "\u9a91\u58eb", "displayConference": "\u4e1c\u90e8", "division": "\u4e2d\u592e\u5206\u533a", "id": "1610612739", "isAllStarTeam": false, "isLeagueTeam": true, "leagueId": "00", "name": "\u9a91\u58eb", "nameEn": "Cavaliers"}, "statAverage": {"assistsPg": 4.7, "blocksPg": 0.3, "defRebsPg": 2.1, "efficiency": 16.8, "fgaPg": 16.585, "fgmPg": 7.434, "fgpct": 44.8, "foulsPg": 2.0, "ftaPg": 3.604, "ftmPg": 3.189, "ftpct": 88.5, "games": 53, "gamesStarted": 53, "minsPg": 31.5, "offRebsPg": 0.8, "pointsPg": 19.6, "rebsPg": 2.9, "stealsPg": 1.0, "tpaPg": 4.943, "tpmPg": 1.585, "tppct": 32.1, "turnoversPg": 2.3}, "statTotal": {"assists": 250, "blocks": 18, "defRebs": 113, "fga": 879, "fgm": 394, "fgpct": 44.8, "fouls": 107, "fta": 191, "ftm": 169, "ftpct": 88.5, "mins": 1667, "offRebs": 44, "points": 1041, "rebs": 157, "secs": 0, "steals": 56, "tpa": 262, "tpm": 84, "tppct": 32.1, "turnovers": 124}, "season": "2015"}, {"profile": {"abbr": "CLE", "city": "\u514b\u5229\u592b\u5170", "cityEn": "Cleveland", "code": "cavaliers", "conference": "Eastern", "displayAbbr": "\u9a91\u58eb", "displayConference": "\u4e1c\u90e8", "division": "\u4e2d\u592e\u5206\u533a", "id": "1610612739", "isAllStarTeam": false, "isLeagueTeam": true, "leagueId": "00", "name": "\u9a91\u58eb", "nameEn": "Cavaliers"}, "statAverage": {"assistsPg": 5.8, "blocksPg": 0.3, "defRebsPg": 2.5, "efficiency": 22.4, "fgaPg": 19.722, "fgmPg": 9.319, "fgpct": 47.3, "foulsPg": 2.2, "ftaPg": 4.556, "ftmPg": 4.125, "ftpct": 90.5, "games": 72, "gamesStarted": 72, "minsPg": 35.1, "offRebsPg": 0.7, "pointsPg": 25.2, "rebsPg": 3.2, "stealsPg": 1.1, "tpaPg": 6.125, "tpmPg": 2.458, "tppct": 40.1, "turnoversPg": 2.5}, "statTotal": {"assists": 418, "blocks": 24, "defRebs": 178, "fga": 1420, "fgm": 671, "fgpct": 47.3, "fouls": 157, "fta": 328, "ftm": 297, "ftpct": 90.5, "mins": 2525, "offRebs": 52, "points": 1816, "rebs": 230, "secs": 0, "steals": 83, "tpa": 441, "tpm": 177, "tppct": 40.1, "turnovers": 180}, "season": "2016"}, {"profile": {"abbr": "BOS", "city": "\u6ce2\u58eb\u987f", "cityEn": "Boston", "code": "celtics", "conference": "Eastern", "displayAbbr": "\u51ef\u5c14\u7279\u4eba", "displayConference": "\u4e1c\u90e8", "division": "\u5927\u897f\u6d0b\u5206\u533a", "id": "1610612738", "isAllStarTeam": false, "isLeagueTeam": true, "leagueId": "00", "name": "\u51ef\u5c14\u7279\u4eba", "nameEn": "Celtics"}, "statAverage": {"assistsPg": 5.1, "blocksPg": 0.2, "defRebsPg": 3.2, "efficiency": 22.7, "fgaPg": 18.117, "fgmPg": 8.9, "fgpct": 49.1, "foulsPg": 2.0, "ftaPg": 4.35, "ftmPg": 3.867, "ftpct": 88.9, "games": 60, "gamesStarted": 60, "minsPg": 32.2, "offRebsPg": 0.6, "pointsPg": 24.4, "rebsPg": 3.8, "stealsPg": 1.0, "tpaPg": 6.783, "tpmPg": 2.767, "tppct": 40.8, "turnoversPg": 2.3}, "statTotal": {"assists": 306, "blocks": 17, "defRebs": 194, "fga": 1087, "fgm": 534, "fgpct": 49.1, "fouls": 122, "fta": 261, "ftm": 232, "ftpct": 88.9, "mins": 1931, "offRebs": 33, "points": 1466, "rebs": 227, "secs": 0, "steals": 65, "tpa": 407, "tpm": 166, "tppct": 40.8, "turnovers": 139}, "season": "2017"}, {"profile": {"abbr": "BOS", "city": "\u6ce2\u58eb\u987f", "cityEn": "Boston", "code": "celtics", "conference": "Eastern", "displayAbbr": "\u51ef\u5c14\u7279\u4eba", "displayConference": "\u4e1c\u90e8", "division": "\u5927\u897f\u6d0b\u5206\u533a", "id": "1610612738", "isAllStarTeam": false, "isLeagueTeam": true, "leagueId": "00", "name": "\u51ef\u5c14\u7279\u4eba", "nameEn": "Celtics"}, "statAverage": {"assistsPg": 6.9, "blocksPg": 0.5, "defRebsPg": 3.9, "efficiency": 25.3, "fgaPg": 18.522, "fgmPg": 9.015, "fgpct": 48.7, "foulsPg": 2.5, "ftaPg": 3.657, "ftmPg": 3.194, "ftpct": 87.3, "games": 67, "gamesStarted": 67, "minsPg": 33.0, "offRebsPg": 1.1, "pointsPg": 23.8, "rebsPg": 5.0, "stealsPg": 1.5, "tpaPg": 6.478, "tpmPg": 2.597, "tppct": 40.1, "turnoversPg": 2.5}, "statTotal": {"assists": 464, "blocks": 34, "defRebs": 264, "fga": 1241, "fgm": 604, "fgpct": 48.7, "fouls": 167, "fta": 245, "ftm": 214, "ftpct": 87.3, "mins": 2214, "offRebs": 71, "points": 1596, "rebs": 335, "secs": 0, "steals": 103, "tpa": 434, "tpm": 174, "tppct": 40.1, "turnovers": 172}, "season": "2018"}, {"profile": {"abbr": "BOS", "city": "\u6ce2\u58eb\u987f", "cityEn": "Boston", "code": "celtics", "conference": "Eastern", "displayAbbr": "\u51ef\u5c14\u7279\u4eba", "displayConference": "\u4e1c\u90e8", "division": "\u5927\u897f\u6d0b\u5206\u533a", "id": "1610612738", "isAllStarTeam": false, "isLeagueTeam": true, "leagueId": "00", "name": "\u51ef\u5c14\u7279\u4eba", "nameEn": "Celtics"}, "statAverage": {"assistsPg": 0.0, "blocksPg": 0.0, "defRebsPg": 0.0, "efficiency": 0.0, "fgaPg": 0.0, "fgmPg": 0.0, "fgpct": 0.0, "foulsPg": 0.0, "ftaPg": 0.0, "ftmPg": 0.0, "ftpct": 0.0, "games": 0, "gamesStarted": 0, "minsPg": 0.0, "offRebsPg": 0.0, "pointsPg": 0.0, "rebsPg": 0.0, "stealsPg": 0.0, "tpaPg": 0.0, "tpmPg": 0.0, "tppct": 0.0, "turnoversPg": 0.0}, "statTotal": {"assists": 0, "blocks": 0, "defRebs": 0, "fga": 0, "fgm": 0, "fgpct": 0.0, "fouls": 0, "fta": 0, "ftm": 0, "ftpct": 0.0, "mins": 0, "offRebs": 0, "points": 0, "rebs": 0, "secs": 0, "steals": 0, "tpa": 0, "tpm": 0, "tppct": 0.0, "turnovers": 0}, "season": "2019"}, {"profile": {"abbr": "BKN", "city": "\u5e03\u9c81\u514b\u6797", "cityEn": "Brooklyn", "code": "nets", "conference": "Eastern", "displayAbbr": "\u7bee\u7f51", "displayConference": "\u4e1c\u90e8", "division": "\u5927\u897f\u6d0b\u5206\u533a", "id": "1610612751", "isAllStarTeam": false, "isLeagueTeam": true, "leagueId": "00", "name": "\u7bee\u7f51", "nameEn": "Nets"}, "statAverage": {"assistsPg": 6.4, "blocksPg": 0.5, "defRebsPg": 4.1, "efficiency": 27.0, "fgaPg": 20.8, "fgmPg": 9.95, "fgpct": 47.8, "foulsPg": 2.7, "ftaPg": 5.1, "ftmPg": 4.7, "ftpct": 92.2, "games": 20, "gamesStarted": 20, "minsPg": 32.9, "offRebsPg": 1.1, "pointsPg": 27.4, "rebsPg": 5.2, "stealsPg": 1.3, "tpaPg": 7.1, "tpmPg": 2.8, "tppct": 39.4, "turnoversPg": 2.6}, "statTotal": {"assists": 128, "blocks": 10, "defRebs": 81, "fga": 416, "fgm": 199, "fgpct": 47.8, "fouls": 53, "fta": 102, "ftm": 94, "ftpct": 92.2, "mins": 658, "offRebs": 22, "points": 548, "rebs": 103, "secs": 0, "steals": 27, "tpa": 142, "tpm": 56, "tppct": 39.4, "turnovers": 52}, "season": "2019"}, {"profile": null, "statAverage": {"assistsPg": 6.4, "blocksPg": 0.5, "defRebsPg": 4.1, "efficiency": 27.0, "fgaPg": 20.8, "fgmPg": 9.95, "fgpct": 47.8, "foulsPg": 2.7, "ftaPg": 5.1, "ftmPg": 4.7, "ftpct": 92.2, "games": 20, "gamesStarted": 20, "minsPg": 32.9, "offRebsPg": 1.1, "pointsPg": 27.4, "rebsPg": 5.2, "stealsPg": 1.4, "tpaPg": 7.1, "tpmPg": 2.8, "tppct": 39.4, "turnoversPg": 2.6}, "statTotal": {"assists": 128, "blocks": 10, "defRebs": 81, "fga": 416, "fgm": 199, "fgpct": 47.8, "fouls": 53, "fta": 102, "ftm": 94, "ftpct": 92.2, "mins": 658, "offRebs": 22, "points": 548, "rebs": 103, "secs": 0, "steals": 27, "tpa": 142, "tpm": 56, "tppct": 39.4, "turnovers": 52}, "season": "2019"}]}, "playoffStat": {"playerTeams": [{"profile": {"abbr": "CLE", "city": "\u514b\u5229\u592b\u5170", "cityEn": "Cleveland", "code": "cavaliers", "conference": "Eastern", "displayAbbr": "\u9a91\u58eb", "displayConference": "\u4e1c\u90e8", "division": "\u4e2d\u592e\u5206\u533a", "id": "1610612739", "isAllStarTeam": false, "isLeagueTeam": true, "leagueId": "00", "name": "\u9a91\u58eb", "nameEn": "Cavaliers"}, "statAverage": {"assistsPg": 3.8, "blocksPg": 0.8, "defRebsPg": 2.8, "efficiency": 18.2, "fgaPg": 14.231, "fgmPg": 6.231, "fgpct": 43.8, "foulsPg": 2.2, "ftaPg": 5.308, "ftmPg": 4.462, "ftpct": 84.1, "games": 13, "gamesStarted": 13, "minsPg": 35.7, "offRebsPg": 0.8, "pointsPg": 19.0, "rebsPg": 3.6, "stealsPg": 1.3, "tpaPg": 4.615, "tpmPg": 2.077, "tppct": 45.0, "turnoversPg": 1.5}, "statTotal": {"assists": 50, "blocks": 11, "defRebs": 37, "fga": 185, "fgm": 81, "fgpct": 43.8, "fouls": 29, "fta": 69, "ftm": 58, "ftpct": 84.1, "mins": 464, "offRebs": 10, "points": 247, "rebs": 47, "secs": 0, "steals": 17, "tpa": 60, "tpm": 27, "tppct": 45.0, "turnovers": 20}, "season": "2014"}, {"profile": {"abbr": "CLE", "city": "\u514b\u5229\u592b\u5170", "cityEn": "Cleveland", "code": "cavaliers", "conference": "Eastern", "displayAbbr": "\u9a91\u58eb", "displayConference": "\u4e1c\u90e8", "division": "\u4e2d\u592e\u5206\u533a", "id": "1610612739", "isAllStarTeam": false, "isLeagueTeam": true, "leagueId": "00", "name": "\u9a91\u58eb", "nameEn": "Cavaliers"}, "statAverage": {"assistsPg": 4.7, "blocksPg": 0.6, "defRebsPg": 2.2, "efficiency": 21.8, "fgaPg": 20.143, "fgmPg": 9.571, "fgpct": 47.5, "foulsPg": 2.2, "ftaPg": 4.19, "ftmPg": 3.667, "ftpct": 87.5, "games": 21, "gamesStarted": 21, "minsPg": 36.8, "offRebsPg": 0.7, "pointsPg": 25.2, "rebsPg": 2.9, "stealsPg": 1.7, "tpaPg": 5.524, "tpmPg": 2.429, "tppct": 44.0, "turnoversPg": 2.2}, "statTotal": {"assists": 98, "blocks": 13, "defRebs": 47, "fga": 423, "fgm": 201, "fgpct": 47.5, "fouls": 46, "fta": 88, "ftm": 77, "ftpct": 87.5, "mins": 774, "offRebs": 15, "points": 530, "rebs": 62, "secs": 0, "steals": 36, "tpa": 116, "tpm": 51, "tppct": 44.0, "turnovers": 48}, "season": "2015"}, {"profile": {"abbr": "CLE", "city": "\u514b\u5229\u592b\u5170", "cityEn": "Cleveland", "code": "cavaliers", "conference": "Eastern", "displayAbbr": "\u9a91\u58eb", "displayConference": "\u4e1c\u90e8", "division": "\u4e2d\u592e\u5206\u533a", "id": "1610612739", "isAllStarTeam": false, "isLeagueTeam": true, "leagueId": "00", "name": "\u9a91\u58eb", "nameEn": "Cavaliers"}, "statAverage": {"assistsPg": 5.3, "blocksPg": 0.4, "defRebsPg": 2.1, "efficiency": 21.7, "fgaPg": 20.556, "fgmPg": 9.611, "fgpct": 46.8, "foulsPg": 2.1, "ftaPg": 4.667, "ftmPg": 4.222, "ftpct": 90.5, "games": 18, "gamesStarted": 18, "minsPg": 36.3, "offRebsPg": 0.7, "pointsPg": 25.9, "rebsPg": 2.8, "stealsPg": 1.2, "tpaPg": 6.556, "tpmPg": 2.444, "tppct": 37.3, "turnoversPg": 2.6}, "statTotal": {"assists": 95, "blocks": 8, "defRebs": 38, "fga": 370, "fgm": 173, "fgpct": 46.8, "fouls": 38, "fta": 84, "ftm": 76, "ftpct": 90.5, "mins": 653, "offRebs": 13, "points": 466, "rebs": 51, "secs": 0, "steals": 23, "tpa": 118, "tpm": 44, "tppct": 37.3, "turnovers": 48}, "season": "2016"}, {"profile": {"abbr": "BOS", "city": "\u6ce2\u58eb\u987f", "cityEn": "Boston", "code": "celtics", "conference": "Eastern", "displayAbbr": "\u51ef\u5c14\u7279\u4eba", "displayConference": "\u4e1c\u90e8", "division": "\u5927\u897f\u6d0b\u5206\u533a", "id": "1610612738", "isAllStarTeam": false, "isLeagueTeam": true, "leagueId": "00", "name": "\u51ef\u5c14\u7279\u4eba", "nameEn": "Celtics"}, "statAverage": {"assistsPg": 0.0, "blocksPg": 0.0, "defRebsPg": 0.0, "efficiency": 0.0, "fgaPg": 0.0, "fgmPg": 0.0, "fgpct": 0.0, "foulsPg": 0.0, "ftaPg": 0.0, "ftmPg": 0.0, "ftpct": 0.0, "games": 0, "gamesStarted": 0, "minsPg": 0.0, "offRebsPg": 0.0, "pointsPg": 0.0, "rebsPg": 0.0, "stealsPg": 0.0, "tpaPg": 0.0, "tpmPg": 0.0, "tppct": 0.0, "turnoversPg": 0.0}, "statTotal": {"assists": 0, "blocks": 0, "defRebs": 0, "fga": 0, "fgm": 0, "fgpct": 0.0, "fouls": 0, "fta": 0, "ftm": 0, "ftpct": 0.0, "mins": 0, "offRebs": 0, "points": 0, "rebs": 0, "secs": 0, "steals": 0, "tpa": 0, "tpm": 0, "tppct": 0.0, "turnovers": 0}, "season": "2017"}, {"profile": {"abbr": "BOS", "city": "\u6ce2\u58eb\u987f", "cityEn": "Boston", "code": "celtics", "conference": "Eastern", "displayAbbr": "\u51ef\u5c14\u7279\u4eba", "displayConference": "\u4e1c\u90e8", "division": "\u5927\u897f\u6d0b\u5206\u533a", "id": "1610612738", "isAllStarTeam": false, "isLeagueTeam": true, "leagueId": "00", "name": "\u51ef\u5c14\u7279\u4eba", "nameEn": "Celtics"}, "statAverage": {"assistsPg": 7.0, "blocksPg": 0.4, "defRebsPg": 3.8, "efficiency": 18.8, "fgaPg": 19.889, "fgmPg": 7.667, "fgpct": 38.5, "foulsPg": 2.9, "ftaPg": 4.444, "ftmPg": 4.0, "ftpct": 90.0, "games": 9, "gamesStarted": 9, "minsPg": 36.7, "offRebsPg": 0.6, "pointsPg": 21.3, "rebsPg": 4.4, "stealsPg": 1.4, "tpaPg": 6.444, "tpmPg": 2.0, "tppct": 31.0, "turnoversPg": 3.1}, "statTotal": {"assists": 63, "blocks": 4, "defRebs": 34, "fga": 179, "fgm": 69, "fgpct": 38.5, "fouls": 26, "fta": 40, "ftm": 36, "ftpct": 90.0, "mins": 330, "offRebs": 5, "points": 192, "rebs": 39, "secs": 0, "steals": 13, "tpa": 58, "tpm": 18, "tppct": 31.0, "turnovers": 28}, "season": "2018"}]}, "allStarStat": {"playerTeams": [{"profile": {"abbr": "EST", "city": "East NBA All Stars", "cityEn": "East NBA All Stars", "code": "east", "conference": "Eastern", "displayAbbr": "\u4e1c\u90e8", "displayConference": "\u4e1c\u90e8", "division": "", "id": "1610616833", "isAllStarTeam": true, "isLeagueTeam": true, "leagueId": "00", "name": "\u4e1c\u90e8\u660e\u661f\u961f", "nameEn": "East"}, "statAverage": {"assistsPg": 4.0, "blocksPg": 0.0, "defRebsPg": 1.0, "efficiency": null, "fgaPg": 11.0, "fgmPg": 6.0, "fgpct": 54.5, "foulsPg": 1.0, "ftaPg": 0.0, "ftmPg": 0.0, "ftpct": 0.0, "games": 1, "gamesStarted": 0, "minsPg": 25.0, "offRebsPg": 2.0, "pointsPg": 15.0, "rebsPg": 3.0, "stealsPg": 0.0, "tpaPg": 6.0, "tpmPg": 3.0, "tppct": 50.0, "turnoversPg": 2.0}, "statTotal": {"assists": 4, "blocks": 0, "defRebs": 1, "fga": 11, "fgm": 6, "fgpct": 54.5, "fouls": 1, "fta": 0, "ftm": 0, "ftpct": 0.0, "mins": 25, "offRebs": 2, "points": 15, "rebs": 3, "secs": 0, "steals": 0, "tpa": 6, "tpm": 3, "tppct": 50.0, "turnovers": 2}, "season": "2012"}, {"profile": {"abbr": "EST", "city": "East NBA All Stars", "cityEn": "East NBA All Stars", "code": "east", "conference": "Eastern", "displayAbbr": "\u4e1c\u90e8", "displayConference": "\u4e1c\u90e8", "division": "", "id": "1610616833", "isAllStarTeam": true, "isLeagueTeam": true, "leagueId": "00", "name": "\u4e1c\u90e8\u660e\u661f\u961f", "nameEn": "East"}, "statAverage": {"assistsPg": 14.0, "blocksPg": 0.0, "defRebsPg": 4.0, "efficiency": null, "fgaPg": 17.0, "fgmPg": 14.0, "fgpct": 82.4, "foulsPg": 4.0, "ftaPg": 0.0, "ftmPg": 0.0, "ftpct": 0.0, "games": 1, "gamesStarted": 1, "minsPg": 34.0, "offRebsPg": 1.0, "pointsPg": 31.0, "rebsPg": 5.0, "stealsPg": 0.0, "tpaPg": 6.0, "tpmPg": 3.0, "tppct": 50.0, "turnoversPg": 5.0}, "statTotal": {"assists": 14, "blocks": 0, "defRebs": 4, "fga": 17, "fgm": 14, "fgpct": 82.4, "fouls": 4, "fta": 0, "ftm": 0, "ftpct": 0.0, "mins": 34, "offRebs": 1, "points": 31, "rebs": 5, "secs": 0, "steals": 0, "tpa": 6, "tpm": 3, "tppct": 50.0, "turnovers": 5}, "season": "2013"}, {"profile": {"abbr": "EST", "city": "East NBA All Stars", "cityEn": "East NBA All Stars", "code": "east", "conference": "Eastern", "displayAbbr": "\u4e1c\u90e8", "displayConference": "\u4e1c\u90e8", "division": "", "id": "1610616833", "isAllStarTeam": true, "isLeagueTeam": true, "leagueId": "00", "name": "\u4e1c\u90e8\u660e\u661f\u961f", "nameEn": "East"}, "statAverage": {"assistsPg": 5.0, "blocksPg": 0.0, "defRebsPg": 4.0, "efficiency": null, "fgaPg": 9.0, "fgmPg": 4.0, "fgpct": 44.4, "foulsPg": 0.0, "ftaPg": 1.0, "ftmPg": 1.0, "ftpct": 100.0, "games": 1, "gamesStarted": 0, "minsPg": 19.0, "offRebsPg": 2.0, "pointsPg": 11.0, "rebsPg": 6.0, "stealsPg": 0.0, "tpaPg": 6.0, "tpmPg": 2.0, "tppct": 33.3, "turnoversPg": 1.0}, "statTotal": {"assists": 5, "blocks": 0, "defRebs": 4, "fga": 9, "fgm": 4, "fgpct": 44.4, "fouls": 0, "fta": 1, "ftm": 1, "ftpct": 100.0, "mins": 19, "offRebs": 2, "points": 11, "rebs": 6, "secs": 0, "steals": 0, "tpa": 6, "tpm": 2, "tppct": 33.3, "turnovers": 1}, "season": "2014"}, {"profile": {"abbr": "EST", "city": "East NBA All Stars", "cityEn": "East NBA All Stars", "code": "east", "conference": "Eastern", "displayAbbr": "\u4e1c\u90e8", "displayConference": "\u4e1c\u90e8", "division": "", "id": "1610616833", "isAllStarTeam": true, "isLeagueTeam": true, "leagueId": "00", "name": "\u4e1c\u90e8\u660e\u661f\u961f", "nameEn": "East"}, "statAverage": {"assistsPg": 14.0, "blocksPg": 0.0, "defRebsPg": 5.0, "efficiency": null, "fgaPg": 12.0, "fgmPg": 8.0, "fgpct": 66.7, "foulsPg": 1.0, "ftaPg": 0.0, "ftmPg": 0.0, "ftpct": 0.0, "games": 1, "gamesStarted": 1, "minsPg": 22.0, "offRebsPg": 2.0, "pointsPg": 22.0, "rebsPg": 7.0, "stealsPg": 3.0, "tpaPg": 8.0, "tpmPg": 6.0, "tppct": 75.0, "turnoversPg": 2.0}, "statTotal": {"assists": 14, "blocks": 0, "defRebs": 5, "fga": 12, "fgm": 8, "fgpct": 66.7, "fouls": 1, "fta": 0, "ftm": 0, "ftpct": 0.0, "mins": 22, "offRebs": 2, "points": 22, "rebs": 7, "secs": 0, "steals": 3, "tpa": 8, "tpm": 6, "tppct": 75.0, "turnovers": 2}, "season": "2016"}, {"profile": {"abbr": "LBN", "city": "", "cityEn": "Team", "code": "team_lebron", "conference": "Eastern", "displayAbbr": "\u52d2\u5e03\u6717\u961f", "displayConference": "\u4e1c\u90e8", "division": "East", "id": "1610616833", "isAllStarTeam": true, "isLeagueTeam": true, "leagueId": "00", "name": "\u52d2\u5e03\u6717\u961f", "nameEn": "LeBron"}, "statAverage": {"assistsPg": 9.0, "blocksPg": 0.0, "defRebsPg": 5.0, "efficiency": null, "fgaPg": 16.0, "fgmPg": 6.0, "fgpct": 37.5, "foulsPg": 2.0, "ftaPg": 0.0, "ftmPg": 0.0, "ftpct": 0.0, "games": 1, "gamesStarted": 1, "minsPg": 28.0, "offRebsPg": 2.0, "pointsPg": 13.0, "rebsPg": 7.0, "stealsPg": 1.0, "tpaPg": 5.0, "tpmPg": 1.0, "tppct": 20.0, "turnoversPg": 1.0}, "statTotal": {"assists": 9, "blocks": 0, "defRebs": 5, "fga": 16, "fgm": 6, "fgpct": 37.5, "fouls": 2, "fta": 0, "ftm": 0, "ftpct": 0.0, "mins": 28, "offRebs": 2, "points": 13, "rebs": 7, "secs": 0, "steals": 1, "tpa": 5, "tpm": 1, "tppct": 20.0, "turnovers": 1}, "season": "2017"}, {"profile": {"abbr": "LBN", "city": "", "cityEn": "Team", "code": "team_lebron", "conference": "Western", "displayAbbr": "\u52d2\u5e03\u6717\u961f", "displayConference": "\u897f\u90e8", "division": "West", "id": "1610616834", "isAllStarTeam": true, "isLeagueTeam": true, "leagueId": "00", "name": "\u52d2\u5e03\u6717\u961f", "nameEn": "LeBron"}, "statAverage": {"assistsPg": 6.0, "blocksPg": 1.0, "defRebsPg": 5.0, "efficiency": null, "fgaPg": 12.0, "fgmPg": 6.0, "fgpct": 50.0, "foulsPg": 3.0, "ftaPg": 0.0, "ftmPg": 0.0, "ftpct": 0.0, "games": 1, "gamesStarted": 1, "minsPg": 25.0, "offRebsPg": 4.0, "pointsPg": 13.0, "rebsPg": 9.0, "stealsPg": 1.0, "tpaPg": 4.0, "tpmPg": 1.0, "tppct": 25.0, "turnoversPg": 1.0}, "statTotal": {"assists": 6, "blocks": 1, "defRebs": 5, "fga": 12, "fgm": 6, "fgpct": 50.0, "fouls": 3, "fta": 0, "ftm": 0, "ftpct": 0.0, "mins": 25, "offRebs": 4, "points": 13, "rebs": 9, "secs": 0, "steals": 1, "tpa": 4, "tpm": 1, "tppct": 25.0, "turnovers": 1}, "season": "2018"}]}, "seasonGames": [{"profile": {"teamProfile": {"abbr": "BKN", "city": "\u5e03\u9c81\u514b\u6797", "cityEn": "Brooklyn", "code": "nets", "conference": "Eastern", "displayAbbr": "\u7bee\u7f51", "displayConference": "\u4e1c\u90e8", "division": "\u5927\u897f\u6d0b\u5206\u533a", "id": "1610612751", "isAllStarTeam": false, "isLeagueTeam": true, "leagueId": "00", "name": "\u7bee\u7f51", "nameEn": "Nets"}, "oppTeamProfile": {"abbr": "WAS", "city": "\u534e\u76db\u987f", "cityEn": "Washington", "code": "wizards", "conference": "Eastern", "displayAbbr": "\u5947\u624d", "displayConference": "\u4e1c\u90e8", "division": "\u4e1c\u5357\u5206\u533a", "id": "1610612764", "isAllStarTeam": false, "isLeagueTeam": true, "leagueId": "00", "name": "\u5947\u624d", "nameEn": "Wizards"}, "gameId": "0021900731", "isHome": "false", "oppTeamScore": 113, "teamScore": 107, "utcMillis": "1580605200000", "winOrLoss": "Lost"}, "statTotal": {"assists": 4, "blocks": 1, "defRebs": 2, "fga": 12, "fgm": 5, "fgpct": 41.7, "fouls": 4, "fta": 0, "ftm": 0, "ftpct": 0.0, "mins": 29, "offRebs": 2, "points": 11, "rebs": 4, "secs": 38, "steals": 1, "tpa": 5, "tpm": 1, "tppct": 20.0, "turnovers": 6}}, {"profile": {"teamProfile": {"abbr": "BKN", "city": "\u5e03\u9c81\u514b\u6797", "cityEn": "Brooklyn", "code": "nets", "conference": "Eastern", "displayAbbr": "\u7bee\u7f51", "displayConference": "\u4e1c\u90e8", "division": "\u5927\u897f\u6d0b\u5206\u533a", "id": "1610612751", "isAllStarTeam": false, "isLeagueTeam": true, "leagueId": "00", "name": "\u7bee\u7f51", "nameEn": "Nets"}, "oppTeamProfile": {"abbr": "CHI", "city": "\u829d\u52a0\u54e5", "cityEn": "Chicago", "code": "bulls", "conference": "Eastern", "displayAbbr": "\u516c\u725b", "displayConference": "\u4e1c\u90e8", "division": "\u4e2d\u592e\u5206\u533a", "id": "1610612741", "isAllStarTeam": false, "isLeagueTeam": true, "leagueId": "00", "name": "\u516c\u725b", "nameEn": "Bulls"}, "gameId": "0021900721", "isHome": "true", "oppTeamScore": 118, "teamScore": 133, "utcMillis": "1580517000000", "winOrLoss": "Won"}, "statTotal": {"assists": 5, "blocks": 0, "defRebs": 5, "fga": 23, "fgm": 19, "fgpct": 82.6, "fouls": 3, "fta": 10, "ftm": 9, "ftpct": 90.0, "mins": 32, "offRebs": 0, "points": 54, "rebs": 5, "secs": 53, "steals": 1, "tpa": 9, "tpm": 7, "tppct": 77.8, "turnovers": 4}}, {"profile": {"teamProfile": {"abbr": "BKN", "city": "\u5e03\u9c81\u514b\u6797", "cityEn": "Brooklyn", "code": "nets", "conference": "Eastern", "displayAbbr": "\u7bee\u7f51", "displayConference": "\u4e1c\u90e8", "division": "\u5927\u897f\u6d0b\u5206\u533a", "id": "1610612751", "isAllStarTeam": false, "isLeagueTeam": true, "leagueId": "00", "name": "\u7bee\u7f51", "nameEn": "Nets"}, "oppTeamProfile": {"abbr": "DET", "city": "\u5e95\u7279\u5f8b", "cityEn": "Detroit", "code": "pistons", "conference": "Eastern", "displayAbbr": "\u6d3b\u585e", "displayConference": "\u4e1c\u90e8", "division": "\u4e2d\u592e\u5206\u533a", "id": "1610612765", "isAllStarTeam": false, "isLeagueTeam": true, "leagueId": "00", "name": "\u6d3b\u585e", "nameEn": "Pistons"}, "gameId": "0021900709", "isHome": "true", "oppTeamScore": 115, "teamScore": 125, "utcMillis": "1580344200000", "winOrLoss": "Won"}, "statTotal": {"assists": 5, "blocks": 0, "defRebs": 2, "fga": 16, "fgm": 7, "fgpct": 43.8, "fouls": 2, "fta": 4, "ftm": 4, "ftpct": 100.0, "mins": 33, "offRebs": 3, "points": 20, "rebs": 5, "secs": 50, "steals": 2, "tpa": 5, "tpm": 2, "tppct": 40.0, "turnovers": 4}}, {"profile": {"teamProfile": {"abbr": "BKN", "city": "\u5e03\u9c81\u514b\u6797", "cityEn": "Brooklyn", "code": "nets", "conference": "Eastern", "displayAbbr": "\u7bee\u7f51", "displayConference": "\u4e1c\u90e8", "division": "\u5927\u897f\u6d0b\u5206\u533a", "id": "1610612751", "isAllStarTeam": false, "isLeagueTeam": true, "leagueId": "00", "name": "\u7bee\u7f51", "nameEn": "Nets"}, "oppTeamProfile": {"abbr": "DET", "city": "\u5e95\u7279\u5f8b", "cityEn": "Detroit", "code": "pistons", "conference": "Eastern", "displayAbbr": "\u6d3b\u585e", "displayConference": "\u4e1c\u90e8", "division": "\u4e2d\u592e\u5206\u533a", "id": "1610612765", "isAllStarTeam": false, "isLeagueTeam": true, "leagueId": "00", "name": "\u6d3b\u585e", "nameEn": "Pistons"}, "gameId": "0021900681", "isHome": "false", "oppTeamScore": 111, "teamScore": 121, "utcMillis": "1579996800000", "winOrLoss": "Won"}, "statTotal": {"assists": 7, "blocks": 0, "defRebs": 6, "fga": 30, "fgm": 15, "fgpct": 50.0, "fouls": 5, "fta": 10, "ftm": 10, "ftpct": 100.0, "mins": 40, "offRebs": 0, "points": 45, "rebs": 6, "secs": 1, "steals": 0, "tpa": 12, "tpm": 5, "tppct": 41.7, "turnovers": 1}}, {"profile": {"teamProfile": {"abbr": "BKN", "city": "\u5e03\u9c81\u514b\u6797", "cityEn": "Brooklyn", "code": "nets", "conference": "Eastern", "displayAbbr": "\u7bee\u7f51", "displayConference": "\u4e1c\u90e8", "division": "\u5927\u897f\u6d0b\u5206\u533a", "id": "1610612751", "isAllStarTeam": false, "isLeagueTeam": true, "leagueId": "00", "name": "\u7bee\u7f51", "nameEn": "Nets"}, "oppTeamProfile": {"abbr": "LAL", "city": "\u6d1b\u6749\u77f6", "cityEn": "Los Angeles", "code": "lakers", "conference": "Western", "displayAbbr": "\u6e56\u4eba", "displayConference": "\u897f\u90e8", "division": "\u592a\u5e73\u6d0b\u5206\u533a", "id": "1610612747", "isAllStarTeam": false, "isLeagueTeam": true, "leagueId": "00", "name": "\u6e56\u4eba", "nameEn": "Lakers"}, "gameId": "0021900667", "isHome": "true", "oppTeamScore": 128, "teamScore": 113, "utcMillis": "1579827600000", "winOrLoss": "Lost"}, "statTotal": {"assists": 4, "blocks": 1, "defRebs": 2, "fga": 17, "fgm": 7, "fgpct": 41.2, "fouls": 2, "fta": 4, "ftm": 3, "ftpct": 75.0, "mins": 33, "offRebs": 1, "points": 20, "rebs": 3, "secs": 12, "steals": 2, "tpa": 6, "tpm": 3, "tppct": 50.0, "turnovers": 4}}, {"profile": {"teamProfile": {"abbr": "BKN", "city": "\u5e03\u9c81\u514b\u6797", "cityEn": "Brooklyn", "code": "nets", "conference": "Eastern", "displayAbbr": "\u7bee\u7f51", "displayConference": "\u4e1c\u90e8", "division": "\u5927\u897f\u6d0b\u5206\u533a", "id": "1610612751", "isAllStarTeam": false, "isLeagueTeam": true, "leagueId": "00", "name": "\u7bee\u7f51", "nameEn": "Nets"}, "oppTeamProfile": {"abbr": "MIL", "city": "\u5bc6\u5c14\u6c83\u57fa", "cityEn": "Milwaukee", "code": "bucks", "conference": "Eastern", "displayAbbr": "\u96c4\u9e7f", "displayConference": "\u4e1c\u90e8", "division": "\u4e2d\u592e\u5206\u533a", "id": "1610612749", "isAllStarTeam": false, "isLeagueTeam": true, "leagueId": "00", "name": "\u96c4\u9e7f", "nameEn": "Bucks"}, "gameId": "0021900627", "isHome": "true", "oppTeamScore": 117, "teamScore": 97, "utcMillis": "1579388400000", "winOrLoss": "Lost"}, "statTotal": {"assists": 6, "blocks": 0, "defRebs": 5, "fga": 15, "fgm": 6, "fgpct": 40.0, "fouls": 2, "fta": 3, "ftm": 3, "ftpct": 100.0, "mins": 31, "offRebs": 1, "points": 17, "rebs": 6, "secs": 39, "steals": 4, "tpa": 6, "tpm": 2, "tppct": 33.3, "turnovers": 2}}, {"profile": {"teamProfile": {"abbr": "BKN", "city": "\u5e03\u9c81\u514b\u6797", "cityEn": "Brooklyn", "code": "nets", "conference": "Eastern", "displayAbbr": "\u7bee\u7f51", "displayConference": "\u4e1c\u90e8", "division": "\u5927\u897f\u6d0b\u5206\u533a", "id": "1610612751", "isAllStarTeam": false, "isLeagueTeam": true, "leagueId": "00", "name": "\u7bee\u7f51", "nameEn": "Nets"}, "oppTeamProfile": {"abbr": "PHI", "city": "\u8d39\u57ce", "cityEn": "Philadelphia", "code": "sixers", "conference": "Eastern", "displayAbbr": "76\u4eba", "displayConference": "\u4e1c\u90e8", "division": "\u5927\u897f\u6d0b\u5206\u533a", "id": "1610612755", "isAllStarTeam": false, "isLeagueTeam": true, "leagueId": "00", "name": "76\u4eba", "nameEn": "Sixers"}, "gameId": "0021900605", "isHome": "false", "oppTeamScore": 117, "teamScore": 106, "utcMillis": "1579132800000", "winOrLoss": "Lost"}, "statTotal": {"assists": 4, "blocks": 1, "defRebs": 3, "fga": 21, "fgm": 6, "fgpct": 28.6, "fouls": 2, "fta": 2, "ftm": 1, "ftpct": 50.0, "mins": 37, "offRebs": 3, "points": 14, "rebs": 6, "secs": 48, "steals": 2, "tpa": 2, "tpm": 1, "tppct": 50.0, "turnovers": 2}}, {"profile": {"teamProfile": {"abbr": "BKN", "city": "\u5e03\u9c81\u514b\u6797", "cityEn": "Brooklyn", "code": "nets", "conference": "Eastern", "displayAbbr": "\u7bee\u7f51", "displayConference": "\u4e1c\u90e8", "division": "\u5927\u897f\u6d0b\u5206\u533a", "id": "1610612751", "isAllStarTeam": false, "isLeagueTeam": true, "leagueId": "00", "name": "\u7bee\u7f51", "nameEn": "Nets"}, "oppTeamProfile": {"abbr": "UTA", "city": "\u72b9\u4ed6", "cityEn": "Utah", "code": "jazz", "conference": "Western", "displayAbbr": "\u7235\u58eb", "displayConference": "\u897f\u90e8", "division": "\u897f\u5317\u5206\u533a", "id": "1610612762", "isAllStarTeam": false, "isLeagueTeam": true, "leagueId": "00", "name": "\u7235\u58eb", "nameEn": "Jazz"}, "gameId": "0021900599", "isHome": "true", "oppTeamScore": 118, "teamScore": 107, "utcMillis": "1579048200000", "winOrLoss": "Lost"}, "statTotal": {"assists": 11, "blocks": 1, "defRebs": 3, "fga": 19, "fgm": 12, "fgpct": 63.2, "fouls": 0, "fta": 6, "ftm": 5, "ftpct": 83.3, "mins": 32, "offRebs": 2, "points": 32, "rebs": 5, "secs": 13, "steals": 2, "tpa": 5, "tpm": 3, "tppct": 60.0, "turnovers": 1}}, {"profile": {"teamProfile": {"abbr": "BKN", "city": "\u5e03\u9c81\u514b\u6797", "cityEn": "Brooklyn", "code": "nets", "conference": "Eastern", "displayAbbr": "\u7bee\u7f51", "displayConference": "\u4e1c\u90e8", "division": "\u5927\u897f\u6d0b\u5206\u533a", "id": "1610612751", "isAllStarTeam": false, "isLeagueTeam": true, "leagueId": "00", "name": "\u7bee\u7f51", "nameEn": "Nets"}, "oppTeamProfile": {"abbr": "ATL", "city": "\u4e9a\u7279\u5170\u5927", "cityEn": "Atlanta", "code": "hawks", "conference": "Eastern", "displayAbbr": "\u8001\u9e70", "displayConference": "\u4e1c\u90e8", "division": "\u4e1c\u5357\u5206\u533a", "id": "1610612737", "isAllStarTeam": false, "isLeagueTeam": true, "leagueId": "00", "name": "\u8001\u9e70", "nameEn": "Hawks"}, "gameId": "0021900586", "isHome": "true", "oppTeamScore": 86, "teamScore": 108, "utcMillis": "1578870000000", "winOrLoss": "Won"}, "statTotal": {"assists": 3, "blocks": 0, "defRebs": 4, "fga": 11, "fgm": 10, "fgpct": 90.9, "fouls": 1, "fta": 0, "ftm": 0, "ftpct": 0.0, "mins": 20, "offRebs": 0, "points": 21, "rebs": 4, "secs": 46, "steals": 1, "tpa": 1, "tpm": 1, "tppct": 100.0, "turnovers": 2}}, {"profile": {"teamProfile": {"abbr": "BKN", "city": "\u5e03\u9c81\u514b\u6797", "cityEn": "Brooklyn", "code": "nets", "conference": "Eastern", "displayAbbr": "\u7bee\u7f51", "displayConference": "\u4e1c\u90e8", "division": "\u5927\u897f\u6d0b\u5206\u533a", "id": "1610612751", "isAllStarTeam": false, "isLeagueTeam": true, "leagueId": "00", "name": "\u7bee\u7f51", "nameEn": "Nets"}, "oppTeamProfile": {"abbr": "DEN", "city": "\u4e39\u4f5b", "cityEn": "Denver", "code": "nuggets", "conference": "Western", "displayAbbr": "\u6398\u91d1", "displayConference": "\u897f\u90e8", "division": "\u897f\u5317\u5206\u533a", "id": "1610612743", "isAllStarTeam": false, "isLeagueTeam": true, "leagueId": "00", "name": "\u6398\u91d1", "nameEn": "Nuggets"}, "gameId": "0021900166", "isHome": "false", "oppTeamScore": 101, "teamScore": 93, "utcMillis": "1573788600000", "winOrLoss": "Lost"}, "statTotal": {"assists": 9, "blocks": 0, "defRebs": 5, "fga": 20, "fgm": 8, "fgpct": 40.0, "fouls": 4, "fta": 0, "ftm": 0, "ftpct": 0.0, "mins": 35, "offRebs": 1, "points": 17, "rebs": 6, "secs": 43, "steals": 1, "tpa": 5, "tpm": 1, "tppct": 20.0, "turnovers": 0}}, {"profile": {"teamProfile": {"abbr": "BKN", "city": "\u5e03\u9c81\u514b\u6797", "cityEn": "Brooklyn", "code": "nets", "conference": "Eastern", "displayAbbr": "\u7bee\u7f51", "displayConference": "\u4e1c\u90e8", "division": "\u5927\u897f\u6d0b\u5206\u533a", "id": "1610612751", "isAllStarTeam": false, "isLeagueTeam": true, "leagueId": "00", "name": "\u7bee\u7f51", "nameEn": "Nets"}, "oppTeamProfile": {"abbr": "UTA", "city": "\u72b9\u4ed6", "cityEn": "Utah", "code": "jazz", "conference": "Western", "displayAbbr": "\u7235\u58eb", "displayConference": "\u897f\u90e8", "division": "\u897f\u5317\u5206\u533a", "id": "1610612762", "isAllStarTeam": false, "isLeagueTeam": true, "leagueId": "00", "name": "\u7235\u58eb", "nameEn": "Jazz"}, "gameId": "0021900152", "isHome": "false", "oppTeamScore": 119, "teamScore": 114, "utcMillis": "1573610400000", "winOrLoss": "Lost"}, "statTotal": {"assists": 5, "blocks": 1, "defRebs": 2, "fga": 30, "fgm": 10, "fgpct": 33.3, "fouls": 4, "fta": 5, "ftm": 5, "ftpct": 100.0, "mins": 37, "offRebs": 1, "points": 27, "rebs": 3, "secs": 41, "steals": 1, "tpa": 12, "tpm": 2, "tppct": 16.7, "turnovers": 4}}, {"profile": {"teamProfile": {"abbr": "BKN", "city": "\u5e03\u9c81\u514b\u6797", "cityEn": "Brooklyn", "code": "nets", "conference": "Eastern", "displayAbbr": "\u7bee\u7f51", "displayConference": "\u4e1c\u90e8", "division": "\u5927\u897f\u6d0b\u5206\u533a", "id": "1610612751", "isAllStarTeam": false, "isLeagueTeam": true, "leagueId": "00", "name": "\u7bee\u7f51", "nameEn": "Nets"}, "oppTeamProfile": {"abbr": "PHX", "city": "\u83f2\u5c3c\u514b\u65af", "cityEn": "Phoenix", "code": "suns", "conference": "Western", "displayAbbr": "\u592a\u9633", "displayConference": "\u897f\u90e8", "division": "\u592a\u5e73\u6d0b\u5206\u533a", "id": "1610612756", "isAllStarTeam": false, "isLeagueTeam": true, "leagueId": "00", "name": "\u592a\u9633", "nameEn": "Suns"}, "gameId": "0021900137", "isHome": "false", "oppTeamScore": 138, "teamScore": 112, "utcMillis": "1573434000000", "winOrLoss": "Lost"}, "statTotal": {"assists": 5, "blocks": 0, "defRebs": 3, "fga": 16, "fgm": 7, "fgpct": 43.8, "fouls": 2, "fta": 0, "ftm": 0, "ftpct": 0.0, "mins": 25, "offRebs": 1, "points": 15, "rebs": 4, "secs": 7, "steals": 0, "tpa": 6, "tpm": 1, "tppct": 16.7, "turnovers": 1}}, {"profile": {"teamProfile": {"abbr": "BKN", "city": "\u5e03\u9c81\u514b\u6797", "cityEn": "Brooklyn", "code": "nets", "conference": "Eastern", "displayAbbr": "\u7bee\u7f51", "displayConference": "\u4e1c\u90e8", "division": "\u5927\u897f\u6d0b\u5206\u533a", "id": "1610612751", "isAllStarTeam": false, "isLeagueTeam": true, "leagueId": "00", "name": "\u7bee\u7f51", "nameEn": "Nets"}, "oppTeamProfile": {"abbr": "POR", "city": "\u6ce2\u7279\u5170", "cityEn": "Portland", "code": "blazers", "conference": "Western", "displayAbbr": "\u5f00\u62d3\u8005", "displayConference": "\u897f\u90e8", "division": "\u897f\u5317\u5206\u533a", "id": "1610612757", "isAllStarTeam": false, "isLeagueTeam": true, "leagueId": "00", "name": "\u5f00\u62d3\u8005", "nameEn": "Trail Blazers"}, "gameId": "0021900125", "isHome": "false", "oppTeamScore": 115, "teamScore": 119, "utcMillis": "1573268400000", "winOrLoss": "Won"}, "statTotal": {"assists": 6, "blocks": 1, "defRebs": 2, "fga": 27, "fgm": 12, "fgpct": 44.4, "fouls": 3, "fta": 5, "ftm": 5, "ftpct": 100.0, "mins": 39, "offRebs": 1, "points": 33, "rebs": 3, "secs": 31, "steals": 1, "tpa": 8, "tpm": 4, "tppct": 50.0, "turnovers": 1}}, {"profile": {"teamProfile": {"abbr": "BKN", "city": "\u5e03\u9c81\u514b\u6797", "cityEn": "Brooklyn", "code": "nets", "conference": "Eastern", "displayAbbr": "\u7bee\u7f51", "displayConference": "\u4e1c\u90e8", "division": "\u5927\u897f\u6d0b\u5206\u533a", "id": "1610612751", "isAllStarTeam": false, "isLeagueTeam": true, "leagueId": "00", "name": "\u7bee\u7f51", "nameEn": "Nets"}, "oppTeamProfile": {"abbr": "NOP", "city": "\u65b0\u5965\u5c14\u826f", "cityEn": "New Orleans", "code": "pelicans", "conference": "Western", "displayAbbr": "\u9e48\u9e55", "displayConference": "\u897f\u90e8", "division": "\u897f\u5357\u5206\u533a", "id": "1610612740", "isAllStarTeam": false, "isLeagueTeam": true, "leagueId": "00", "name": "\u9e48\u9e55", "nameEn": "Pelicans"}, "gameId": "0021900092", "isHome": "true", "oppTeamScore": 125, "teamScore": 135, "utcMillis": "1572913800000", "winOrLoss": "Won"}, "statTotal": {"assists": 9, "blocks": 0, "defRebs": 3, "fga": 21, "fgm": 13, "fgpct": 61.9, "fouls": 2, "fta": 11, "ftm": 11, "ftpct": 100.0, "mins": 35, "offRebs": 1, "points": 39, "rebs": 4, "secs": 33, "steals": 3, "tpa": 6, "tpm": 2, "tppct": 33.3, "turnovers": 5}}, {"profile": {"teamProfile": {"abbr": "BKN", "city": "\u5e03\u9c81\u514b\u6797", "cityEn": "Brooklyn", "code": "nets", "conference": "Eastern", "displayAbbr": "\u7bee\u7f51", "displayConference": "\u4e1c\u90e8", "division": "\u5927\u897f\u6d0b\u5206\u533a", "id": "1610612751", "isAllStarTeam": false, "isLeagueTeam": true, "leagueId": "00", "name": "\u7bee\u7f51", "nameEn": "Nets"}, "oppTeamProfile": {"abbr": "DET", "city": "\u5e95\u7279\u5f8b", "cityEn": "Detroit", "code": "pistons", "conference": "Eastern", "displayAbbr": "\u6d3b\u585e", "displayConference": "\u4e1c\u90e8", "division": "\u4e2d\u592e\u5206\u533a", "id": "1610612765", "isAllStarTeam": false, "isLeagueTeam": true, "leagueId": "00", "name": "\u6d3b\u585e", "nameEn": "Pistons"}, "gameId": "0021900078", "isHome": "false", "oppTeamScore": 113, "teamScore": 109, "utcMillis": "1572735600000", "winOrLoss": "Lost"}, "statTotal": {"assists": 10, "blocks": 0, "defRebs": 10, "fga": 21, "fgm": 8, "fgpct": 38.1, "fouls": 3, "fta": 4, "ftm": 4, "ftpct": 100.0, "mins": 33, "offRebs": 1, "points": 20, "rebs": 11, "secs": 11, "steals": 0, "tpa": 6, "tpm": 0, "tppct": 0.0, "turnovers": 2}}, {"profile": {"teamProfile": {"abbr": "BKN", "city": "\u5e03\u9c81\u514b\u6797", "cityEn": "Brooklyn", "code": "nets", "conference": "Eastern", "displayAbbr": "\u7bee\u7f51", "displayConference": "\u4e1c\u90e8", "division": "\u5927\u897f\u6d0b\u5206\u533a", "id": "1610612751", "isAllStarTeam": false, "isLeagueTeam": true, "leagueId": "00", "name": "\u7bee\u7f51", "nameEn": "Nets"}, "oppTeamProfile": {"abbr": "HOU", "city": "\u4f11\u65af\u987f", "cityEn": "Houston", "code": "rockets", "conference": "Western", "displayAbbr": "\u706b\u7bad", "displayConference": "\u897f\u90e8", "division": "\u897f\u5357\u5206\u533a", "id": "1610612745", "isAllStarTeam": false, "isLeagueTeam": true, "leagueId": "00", "name": "\u706b\u7bad", "nameEn": "Rockets"}, "gameId": "0021900069", "isHome": "true", "oppTeamScore": 116, "teamScore": 123, "utcMillis": "1572649200000", "winOrLoss": "Won"}, "statTotal": {"assists": 10, "blocks": 1, "defRebs": 4, "fga": 18, "fgm": 7, "fgpct": 38.9, "fouls": 3, "fta": 4, "ftm": 3, "ftpct": 75.0, "mins": 34, "offRebs": 0, "points": 22, "rebs": 4, "secs": 29, "steals": 0, "tpa": 8, "tpm": 5, "tppct": 62.5, "turnovers": 6}}, {"profile": {"teamProfile": {"abbr": "BKN", "city": "\u5e03\u9c81\u514b\u6797", "cityEn": "Brooklyn", "code": "nets", "conference": "Eastern", "displayAbbr": "\u7bee\u7f51", "displayConference": "\u4e1c\u90e8", "division": "\u5927\u897f\u6d0b\u5206\u533a", "id": "1610612751", "isAllStarTeam": false, "isLeagueTeam": true, "leagueId": "00", "name": "\u7bee\u7f51", "nameEn": "Nets"}, "oppTeamProfile": {"abbr": "IND", "city": "\u5370\u7b2c\u5b89\u7eb3", "cityEn": "Indiana", "code": "pacers", "conference": "Eastern", "displayAbbr": "\u6b65\u884c\u8005", "displayConference": "\u4e1c\u90e8", "division": "\u4e2d\u592e\u5206\u533a", "id": "1610612754", "isAllStarTeam": false, "isLeagueTeam": true, "leagueId": "00", "name": "\u6b65\u884c\u8005", "nameEn": "Pacers"}, "gameId": "0021900059", "isHome": "true", "oppTeamScore": 118, "teamScore": 108, "utcMillis": "1572478200000", "winOrLoss": "Lost"}, "statTotal": {"assists": 6, "blocks": 1, "defRebs": 7, "fga": 20, "fgm": 11, "fgpct": 55.0, "fouls": 1, "fta": 5, "ftm": 4, "ftpct": 80.0, "mins": 31, "offRebs": 0, "points": 28, "rebs": 7, "secs": 58, "steals": 1, "tpa": 6, "tpm": 2, "tppct": 33.3, "turnovers": 1}}, {"profile": {"teamProfile": {"abbr": "BKN", "city": "\u5e03\u9c81\u514b\u6797", "cityEn": "Brooklyn", "code": "nets", "conference": "Eastern", "displayAbbr": "\u7bee\u7f51", "displayConference": "\u4e1c\u90e8", "division": "\u5927\u897f\u6d0b\u5206\u533a", "id": "1610612751", "isAllStarTeam": false, "isLeagueTeam": true, "leagueId": "00", "name": "\u7bee\u7f51", "nameEn": "Nets"}, "oppTeamProfile": {"abbr": "MEM", "city": "\u5b5f\u83f2\u65af", "cityEn": "Memphis", "code": "grizzlies", "conference": "Western", "displayAbbr": "\u7070\u718a", "displayConference": "\u897f\u90e8", "division": "\u897f\u5357\u5206\u533a", "id": "1610612763", "isAllStarTeam": false, "isLeagueTeam": true, "leagueId": "00", "name": "\u7070\u718a", "nameEn": "Grizzlies"}, "gameId": "0021900037", "isHome": "false", "oppTeamScore": 134, "teamScore": 133, "utcMillis": "1572213600000", "winOrLoss": "Lost"}, "statTotal": {"assists": 7, "blocks": 1, "defRebs": 6, "fga": 27, "fgm": 11, "fgpct": 40.7, "fouls": 1, "fta": 11, "ftm": 10, "ftpct": 90.9, "mins": 34, "offRebs": 1, "points": 37, "rebs": 7, "secs": 20, "steals": 2, "tpa": 12, "tpm": 5, "tppct": 41.7, "turnovers": 2}}, {"profile": {"teamProfile": {"abbr": "BKN", "city": "\u5e03\u9c81\u514b\u6797", "cityEn": "Brooklyn", "code": "nets", "conference": "Eastern", "displayAbbr": "\u7bee\u7f51", "displayConference": "\u4e1c\u90e8", "division": "\u5927\u897f\u6d0b\u5206\u533a", "id": "1610612751", "isAllStarTeam": false, "isLeagueTeam": true, "leagueId": "00", "name": "\u7bee\u7f51", "nameEn": "Nets"}, "oppTeamProfile": {"abbr": "NYK", "city": "\u7ebd\u7ea6", "cityEn": "New York", "code": "knicks", "conference": "Eastern", "displayAbbr": "\u5c3c\u514b\u65af", "displayConference": "\u4e1c\u90e8", "division": "\u5927\u897f\u6d0b\u5206\u533a", "id": "1610612752", "isAllStarTeam": false, "isLeagueTeam": true, "leagueId": "00", "name": "\u5c3c\u514b\u65af", "nameEn": "Knicks"}, "gameId": "0021900019", "isHome": "true", "oppTeamScore": 109, "teamScore": 113, "utcMillis": "1572046200000", "winOrLoss": "Won"}, "statTotal": {"assists": 5, "blocks": 0, "defRebs": 1, "fga": 19, "fgm": 8, "fgpct": 42.1, "fouls": 5, "fta": 8, "ftm": 8, "ftpct": 100.0, "mins": 31, "offRebs": 1, "points": 26, "rebs": 2, "secs": 13, "steals": 3, "tpa": 8, "tpm": 2, "tppct": 25.0, "turnovers": 4}}, {"profile": {"teamProfile": {"abbr": "BKN", "city": "\u5e03\u9c81\u514b\u6797", "cityEn": "Brooklyn", "code": "nets", "conference": "Eastern", "displayAbbr": "\u7bee\u7f51", "displayConference": "\u4e1c\u90e8", "division": "\u5927\u897f\u6d0b\u5206\u533a", "id": "1610612751", "isAllStarTeam": false, "isLeagueTeam": true, "leagueId": "00", "name": "\u7bee\u7f51", "nameEn": "Nets"}, "oppTeamProfile": {"abbr": "MIN", "city": "\u660e\u5c3c\u82cf\u8fbe", "cityEn": "Minnesota", "code": "timberwolves", "conference": "Western", "displayAbbr": "\u68ee\u6797\u72fc", "displayConference": "\u897f\u90e8", "division": "\u897f\u5317\u5206\u533a", "id": "1610612750", "isAllStarTeam": false, "isLeagueTeam": true, "leagueId": "00", "name": "\u68ee\u6797\u72fc", "nameEn": "Timberwolves"}, "gameId": "0021900006", "isHome": "true", "oppTeamScore": 127, "teamScore": 126, "utcMillis": "1571873400000", "winOrLoss": "Lost"}, "statTotal": {"assists": 7, "blocks": 1, "defRebs": 6, "fga": 33, "fgm": 17, "fgpct": 51.5, "fouls": 4, "fta": 10, "ftm": 9, "ftpct": 90.0, "mins": 38, "offRebs": 2, "points": 50, "rebs": 8, "secs": 10, "steals": 0, "tpa": 14, "tpm": 7, "tppct": 50.0, "turnovers": 0}}, {"profile": {"teamProfile": {"abbr": "BKN", "city": "\u5e03\u9c81\u514b\u6797", "cityEn": "Brooklyn", "code": "nets", "conference": "Eastern", "displayAbbr": "\u7bee\u7f51", "displayConference": "\u4e1c\u90e8", "division": "\u5927\u897f\u6d0b\u5206\u533a", "id": "1610612751", "isAllStarTeam": false, "isLeagueTeam": true, "leagueId": "00", "name": "\u7bee\u7f51", "nameEn": "Nets"}, "oppTeamProfile": {"abbr": "TOR", "city": "\u591a\u4f26\u591a", "cityEn": "Toronto", "code": "raptors", "conference": "Eastern", "displayAbbr": "\u731b\u9f99", "displayConference": "\u4e1c\u90e8", "division": "\u5927\u897f\u6d0b\u5206\u533a", "id": "1610612761", "isAllStarTeam": false, "isLeagueTeam": true, "leagueId": "00", "name": "\u731b\u9f99", "nameEn": "Raptors"}, "gameId": "0011900075", "isHome": "true", "oppTeamScore": 123, "teamScore": 107, "utcMillis": "1571441400000", "winOrLoss": "Lost"}, "statTotal": {"assists": 4, "blocks": 0, "defRebs": 3, "fga": 17, "fgm": 7, "fgpct": 41.2, "fouls": 1, "fta": 3, "ftm": 3, "ftpct": 100.0, "mins": 25, "offRebs": 0, "points": 19, "rebs": 3, "secs": 56, "steals": 2, "tpa": 5, "tpm": 2, "tppct": 40.0, "turnovers": 4}}, {"profile": {"teamProfile": {"abbr": "BKN", "city": "\u5e03\u9c81\u514b\u6797", "cityEn": "Brooklyn", "code": "nets", "conference": "Eastern", "displayAbbr": "\u7bee\u7f51", "displayConference": "\u4e1c\u90e8", "division": "\u5927\u897f\u6d0b\u5206\u533a", "id": "1610612751", "isAllStarTeam": false, "isLeagueTeam": true, "leagueId": "00", "name": "\u7bee\u7f51", "nameEn": "Nets"}, "oppTeamProfile": {"abbr": "LAL", "city": "\u6d1b\u6749\u77f6", "cityEn": "Los Angeles", "code": "lakers", "conference": "Western", "displayAbbr": "\u6e56\u4eba", "displayConference": "\u897f\u90e8", "division": "\u592a\u5e73\u6d0b\u5206\u533a", "id": "1610612747", "isAllStarTeam": false, "isLeagueTeam": true, "leagueId": "00", "name": "\u6e56\u4eba", "nameEn": "Lakers"}, "gameId": "0011900031", "isHome": "false", "oppTeamScore": 111, "teamScore": 114, "utcMillis": "1570707000000", "winOrLoss": "Won"}, "statTotal": {"assists": 0, "blocks": 0, "defRebs": 0, "fga": 0, "fgm": 0, "fgpct": 0.0, "fouls": 0, "fta": 0, "ftm": 0, "ftpct": 0.0, "mins": 1, "offRebs": 0, "points": 0, "rebs": 0, "secs": 6, "steals": 0, "tpa": 0, "tpm": 0, "tppct": 0.0, "turnovers": 0}}, {"profile": {"teamProfile": {"abbr": "BKN", "city": "\u5e03\u9c81\u514b\u6797", "cityEn": "Brooklyn", "code": "nets", "conference": "Eastern", "displayAbbr": "\u7bee\u7f51", "displayConference": "\u4e1c\u90e8", "division": "\u5927\u897f\u6d0b\u5206\u533a", "id": "1610612751", "isAllStarTeam": false, "isLeagueTeam": true, "leagueId": "00", "name": "\u7bee\u7f51", "nameEn": "Nets"}, "oppTeamProfile": {"abbr": "FRA", "city": "SESI/Franca", "cityEn": "SESI/Franca", "code": "franca", "conference": "Intl", "displayAbbr": "FRA", "displayConference": "Intl", "division": "", "id": "12332", "isAllStarTeam": false, "isLeagueTeam": false, "leagueId": "00", "name": "Basketball Club of Brazil", "nameEn": "Basketball Club of Brazil"}, "gameId": "0011900004", "isHome": "true", "oppTeamScore": 89, "teamScore": 137, "utcMillis": "1570231800000", "winOrLoss": "Won"}, "statTotal": {"assists": 0, "blocks": 0, "defRebs": 0, "fga": 0, "fgm": 0, "fgpct": 0.0, "fouls": 0, "fta": 0, "ftm": 0, "ftpct": 0.0, "mins": 0, "offRebs": 0, "points": 0, "rebs": 0, "secs": 0, "steals": 0, "tpa": 0, "tpm": 0, "tppct": 0.0, "turnovers": 0}}], "regularSeasonCareerStat": {"statAverage": {"assistsPg": 5.7, "blocksPg": 0.3, "defRebsPg": 2.9, "efficiency": null, "fgaPg": 17.674, "fgmPg": 8.231, "fgpct": 46.6, "foulsPg": 2.2, "ftaPg": 4.386, "ftmPg": 3.847, "ftpct": 87.7, "games": 528, "gamesStarted": 528, "minsPg": 33.8, "offRebsPg": 0.8, "pointsPg": 22.4, "rebsPg": 3.7, "stealsPg": 1.32, "tpaPg": 5.436, "tpmPg": 2.119, "tppct": 39.0, "turnoversPg": 2.64}, "statTotal": {"assists": 3013, "blocks": 187, "defRebs": 1548, "fga": 9332, "fgm": 4346, "fgpct": 46.6, "fouls": 1171, "fta": 2316, "ftm": 2031, "ftpct": 87.7, "mins": 17827, "offRebs": 407, "points": 11842, "rebs": 1955, "secs": 0, "steals": 699, "tpa": 2870, "tpm": 1119, "tppct": 39.0, "turnovers": 1394}}, "playoffCareerStat": {"statAverage": {"assistsPg": 5.0, "blocksPg": 0.59, "defRebsPg": 2.6, "efficiency": null, "fgaPg": 18.967, "fgmPg": 8.59, "fgpct": 45.3, "foulsPg": 2.3, "ftaPg": 4.607, "ftmPg": 4.049, "ftpct": 87.9, "games": 61, "gamesStarted": 61, "minsPg": 36.4, "offRebsPg": 0.7, "pointsPg": 23.5, "rebsPg": 3.3, "stealsPg": 1.46, "tpaPg": 5.77, "tpmPg": 2.295, "tppct": 39.8, "turnoversPg": 2.36}, "statTotal": {"assists": 306, "blocks": 36, "defRebs": 156, "fga": 1157, "fgm": 524, "fgpct": 45.3, "fouls": 139, "fta": 281, "ftm": 247, "ftpct": 87.9, "mins": 2222, "offRebs": 43, "points": 1435, "rebs": 199, "secs": 0, "steals": 89, "tpa": 352, "tpm": 140, "tppct": 39.8, "turnovers": 144}}, "playerSplit": {"splits": [{"statAverage": {"assistsPg": 6.0, "blocksPg": 0.6, "defRebsPg": 5.0, "efficiency": null, "fgaPg": 18.0, "fgmPg": 6.333, "fgpct": 35.2, "foulsPg": null, "ftaPg": 2.0, "ftmPg": 1.667, "ftpct": 83.3, "games": 3, "gamesStarted": 3, "minsPg": 33.0, "offRebsPg": 2.0, "pointsPg": 15.0, "rebsPg": 7.0, "stealsPg": 1.0, "tpaPg": 4.333, "tpmPg": 0.667, "tppct": 15.4, "turnoversPg": null}, "statTotal": {"assists": 18, "blocks": 2, "defRebs": 15, "fga": 54, "fgm": 19, "fgpct": 35.2, "fouls": null, "fta": 6, "ftm": 5, "ftpct": 83.3, "mins": 0, "offRebs": 6, "points": 45, "rebs": 21, "secs": 0, "steals": 3, "tpa": 13, "tpm": 2, "tppct": 15.4, "turnovers": null}, "displayName": "\u4f11\u606f0\u5929", "name": "0 Days Rest"}, {"statAverage": {"assistsPg": 7.3, "blocksPg": 0.4, "defRebsPg": 3.8, "efficiency": null, "fgaPg": 22.3, "fgmPg": 11.0, "fgpct": 49.3, "foulsPg": null, "ftaPg": 6.5, "ftmPg": 6.1, "ftpct": 93.8, "games": 10, "gamesStarted": 10, "minsPg": 33.5, "offRebsPg": 0.8, "pointsPg": 31.4, "rebsPg": 4.6, "stealsPg": 1.3, "tpaPg": 8.3, "tpmPg": 3.3, "tppct": 39.8, "turnoversPg": null}, "statTotal": {"assists": 73, "blocks": 4, "defRebs": 38, "fga": 223, "fgm": 110, "fgpct": 49.3, "fouls": null, "fta": 65, "ftm": 61, "ftpct": 93.8, "mins": 0, "offRebs": 8, "points": 314, "rebs": 46, "secs": 0, "steals": 13, "tpa": 83, "tpm": 33, "tppct": 39.8, "turnovers": null}, "displayName": "\u4f11\u606f1\u5929", "name": "1 Days Rest"}, {"statAverage": {"assistsPg": 6.0, "blocksPg": 0.5, "defRebsPg": 6.0, "efficiency": null, "fgaPg": 17.5, "fgmPg": 8.5, "fgpct": 48.6, "foulsPg": null, "ftaPg": 4.0, "ftmPg": 3.5, "ftpct": 87.5, "games": 2, "gamesStarted": 2, "minsPg": 31.0, "offRebsPg": 0.5, "pointsPg": 22.5, "rebsPg": 6.5, "stealsPg": 2.5, "tpaPg": 6.0, "tpmPg": 2.0, "tppct": 33.3, "turnoversPg": null}, "statTotal": {"assists": 12, "blocks": 1, "defRebs": 12, "fga": 35, "fgm": 17, "fgpct": 48.6, "fouls": null, "fta": 8, "ftm": 7, "ftpct": 87.5, "mins": 0, "offRebs": 1, "points": 45, "rebs": 13, "secs": 0, "steals": 5, "tpa": 12, "tpm": 4, "tppct": 33.3, "turnovers": null}, "displayName": "\u4f11\u606f2\u5929", "name": "2 Days Rest"}, {"statAverage": {"assistsPg": 5.5, "blocksPg": 0.5, "defRebsPg": 2.0, "efficiency": null, "fgaPg": 21.5, "fgmPg": 9.5, "fgpct": 44.2, "foulsPg": null, "ftaPg": 4.5, "ftmPg": 4.5, "ftpct": 100.0, "games": 2, "gamesStarted": 2, "minsPg": 35.5, "offRebsPg": 2.0, "pointsPg": 26.5, "rebsPg": 4.0, "stealsPg": 1.5, "tpaPg": 6.5, "tpmPg": 3.0, "tppct": 46.2, "turnoversPg": null}, "statTotal": {"assists": 11, "blocks": 1, "defRebs": 4, "fga": 43, "fgm": 19, "fgpct": 44.2, "fouls": null, "fta": 9, "ftm": 9, "ftpct": 100.0, "mins": 0, "offRebs": 4, "points": 53, "rebs": 8, "secs": 0, "steals": 3, "tpa": 13, "tpm": 6, "tppct": 46.2, "turnovers": null}, "displayName": "\u4f11\u606f3\u5929", "name": "3 Days Rest"}, {"statAverage": {"assistsPg": 4.6, "blocksPg": 0.6, "defRebsPg": 4.0, "efficiency": null, "fgaPg": 20.333, "fgmPg": 11.333, "fgpct": 55.7, "foulsPg": null, "ftaPg": 4.667, "ftmPg": 4.0, "ftpct": 85.7, "games": 3, "gamesStarted": 3, "minsPg": 30.3, "offRebsPg": 1.0, "pointsPg": 30.3, "rebsPg": 5.0, "stealsPg": 1.0, "tpaPg": 7.0, "tpmPg": 3.667, "tppct": 52.4, "turnoversPg": null}, "statTotal": {"assists": 14, "blocks": 2, "defRebs": 12, "fga": 61, "fgm": 34, "fgpct": 55.7, "fouls": null, "fta": 14, "ftm": 12, "ftpct": 85.7, "mins": 0, "offRebs": 3, "points": 91, "rebs": 15, "secs": 0, "steals": 3, "tpa": 21, "tpm": 11, "tppct": 52.4, "turnovers": null}, "displayName": "\u4f11\u606f3+\u5929", "name": "3+ Days Rest"}, {"statAverage": {"assistsPg": 3.0, "blocksPg": 0.0, "defRebsPg": 4.0, "efficiency": null, "fgaPg": 11.0, "fgmPg": 10.0, "fgpct": 90.9, "foulsPg": null, "ftaPg": 0.0, "ftmPg": 0.0, "ftpct": 0.0, "games": 1, "gamesStarted": 1, "minsPg": 20.0, "offRebsPg": 0.0, "pointsPg": 21.0, "rebsPg": 4.0, "stealsPg": 1.0, "tpaPg": 1.0, "tpmPg": 1.0, "tppct": 100.0, "turnoversPg": null}, "statTotal": {"assists": 3, "blocks": 0, "defRebs": 4, "fga": 11, "fgm": 10, "fgpct": 90.9, "fouls": null, "fta": 0, "ftm": 0, "ftpct": 0.0, "mins": 0, "offRebs": 0, "points": 21, "rebs": 4, "secs": 0, "steals": 1, "tpa": 1, "tpm": 1, "tppct": 100.0, "turnovers": null}, "displayName": "\u5bf9\u9635 \u8001\u9e70", "name": "Against Atl"}, {"statAverage": {"assistsPg": 5.0, "blocksPg": 0.0, "defRebsPg": 5.0, "efficiency": null, "fgaPg": 23.0, "fgmPg": 19.0, "fgpct": 82.6, "foulsPg": null, "ftaPg": 10.0, "ftmPg": 9.0, "ftpct": 90.0, "games": 1, "gamesStarted": 1, "minsPg": 32.0, "offRebsPg": 0.0, "pointsPg": 54.0, "rebsPg": 5.0, "stealsPg": 1.0, "tpaPg": 9.0, "tpmPg": 7.0, "tppct": 77.8, "turnoversPg": null}, "statTotal": {"assists": 5, "blocks": 0, "defRebs": 5, "fga": 23, "fgm": 19, "fgpct": 82.6, "fouls": null, "fta": 10, "ftm": 9, "ftpct": 90.0, "mins": 0, "offRebs": 0, "points": 54, "rebs": 5, "secs": 0, "steals": 1, "tpa": 9, "tpm": 7, "tppct": 77.8, "turnovers": null}, "displayName": "\u5bf9\u9635 \u516c\u725b", "name": "Against Chi"}, {"statAverage": {"assistsPg": 9.0, "blocksPg": 0.0, "defRebsPg": 5.0, "efficiency": null, "fgaPg": 20.0, "fgmPg": 8.0, "fgpct": 40.0, "foulsPg": null, "ftaPg": 0.0, "ftmPg": 0.0, "ftpct": 0.0, "games": 1, "gamesStarted": 1, "minsPg": 35.0, "offRebsPg": 1.0, "pointsPg": 17.0, "rebsPg": 6.0, "stealsPg": 1.0, "tpaPg": 5.0, "tpmPg": 1.0, "tppct": 20.0, "turnoversPg": null}, "statTotal": {"assists": 9, "blocks": 0, "defRebs": 5, "fga": 20, "fgm": 8, "fgpct": 40.0, "fouls": null, "fta": 0, "ftm": 0, "ftpct": 0.0, "mins": 0, "offRebs": 1, "points": 17, "rebs": 6, "secs": 0, "steals": 1, "tpa": 5, "tpm": 1, "tppct": 20.0, "turnovers": null}, "displayName": "\u5bf9\u9635 \u6398\u91d1", "name": "Against Den"}, {"statAverage": {"assistsPg": 7.3, "blocksPg": 0.0, "defRebsPg": 6.0, "efficiency": null, "fgaPg": 22.333, "fgmPg": 10.0, "fgpct": 44.8, "foulsPg": null, "ftaPg": 6.0, "ftmPg": 6.0, "ftpct": 100.0, "games": 3, "gamesStarted": 3, "minsPg": 35.3, "offRebsPg": 1.3, "pointsPg": 28.3, "rebsPg": 7.3, "stealsPg": 0.6, "tpaPg": 7.667, "tpmPg": 2.333, "tppct": 30.4, "turnoversPg": null}, "statTotal": {"assists": 22, "blocks": 0, "defRebs": 18, "fga": 67, "fgm": 30, "fgpct": 44.8, "fouls": null, "fta": 18, "ftm": 18, "ftpct": 100.0, "mins": 0, "offRebs": 4, "points": 85, "rebs": 22, "secs": 0, "steals": 2, "tpa": 23, "tpm": 7, "tppct": 30.4, "turnovers": null}, "displayName": "\u5bf9\u9635 \u6d3b\u585e", "name": "Against Det"}, {"statAverage": {"assistsPg": 10.0, "blocksPg": 1.0, "defRebsPg": 4.0, "efficiency": null, "fgaPg": 18.0, "fgmPg": 7.0, "fgpct": 38.9, "foulsPg": null, "ftaPg": 4.0, "ftmPg": 3.0, "ftpct": 75.0, "games": 1, "gamesStarted": 1, "minsPg": 34.0, "offRebsPg": 0.0, "pointsPg": 22.0, "rebsPg": 4.0, "stealsPg": 0.0, "tpaPg": 8.0, "tpmPg": 5.0, "tppct": 62.5, "turnoversPg": null}, "statTotal": {"assists": 10, "blocks": 1, "defRebs": 4, "fga": 18, "fgm": 7, "fgpct": 38.9, "fouls": null, "fta": 4, "ftm": 3, "ftpct": 75.0, "mins": 0, "offRebs": 0, "points": 22, "rebs": 4, "secs": 0, "steals": 0, "tpa": 8, "tpm": 5, "tppct": 62.5, "turnovers": null}, "displayName": "\u5bf9\u9635 \u706b\u7bad", "name": "Against Hou"}, {"statAverage": {"assistsPg": 6.0, "blocksPg": 1.0, "defRebsPg": 7.0, "efficiency": null, "fgaPg": 20.0, "fgmPg": 11.0, "fgpct": 55.0, "foulsPg": null, "ftaPg": 5.0, "ftmPg": 4.0, "ftpct": 80.0, "games": 1, "gamesStarted": 1, "minsPg": 31.0, "offRebsPg": 0.0, "pointsPg": 28.0, "rebsPg": 7.0, "stealsPg": 1.0, "tpaPg": 6.0, "tpmPg": 2.0, "tppct": 33.3, "turnoversPg": null}, "statTotal": {"assists": 6, "blocks": 1, "defRebs": 7, "fga": 20, "fgm": 11, "fgpct": 55.0, "fouls": null, "fta": 5, "ftm": 4, "ftpct": 80.0, "mins": 0, "offRebs": 0, "points": 28, "rebs": 7, "secs": 0, "steals": 1, "tpa": 6, "tpm": 2, "tppct": 33.3, "turnovers": null}, "displayName": "\u5bf9\u9635 \u6b65\u884c\u8005", "name": "Against Ind"}, {"statAverage": {"assistsPg": 4.0, "blocksPg": 1.0, "defRebsPg": 2.0, "efficiency": null, "fgaPg": 17.0, "fgmPg": 7.0, "fgpct": 41.2, "foulsPg": null, "ftaPg": 4.0, "ftmPg": 3.0, "ftpct": 75.0, "games": 1, "gamesStarted": 1, "minsPg": 33.0, "offRebsPg": 1.0, "pointsPg": 20.0, "rebsPg": 3.0, "stealsPg": 2.0, "tpaPg": 6.0, "tpmPg": 3.0, "tppct": 50.0, "turnoversPg": null}, "statTotal": {"assists": 4, "blocks": 1, "defRebs": 2, "fga": 17, "fgm": 7, "fgpct": 41.2, "fouls": null, "fta": 4, "ftm": 3, "ftpct": 75.0, "mins": 0, "offRebs": 1, "points": 20, "rebs": 3, "secs": 0, "steals": 2, "tpa": 6, "tpm": 3, "tppct": 50.0, "turnovers": null}, "displayName": "\u5bf9\u9635 \u6e56\u4eba", "name": "Against LAL"}, {"statAverage": {"assistsPg": 7.0, "blocksPg": 1.0, "defRebsPg": 6.0, "efficiency": null, "fgaPg": 27.0, "fgmPg": 11.0, "fgpct": 40.7, "foulsPg": null, "ftaPg": 11.0, "ftmPg": 10.0, "ftpct": 90.9, "games": 1, "gamesStarted": 1, "minsPg": 34.0, "offRebsPg": 1.0, "pointsPg": 37.0, "rebsPg": 7.0, "stealsPg": 2.0, "tpaPg": 12.0, "tpmPg": 5.0, "tppct": 41.7, "turnoversPg": null}, "statTotal": {"assists": 7, "blocks": 1, "defRebs": 6, "fga": 27, "fgm": 11, "fgpct": 40.7, "fouls": null, "fta": 11, "ftm": 10, "ftpct": 90.9, "mins": 0, "offRebs": 1, "points": 37, "rebs": 7, "secs": 0, "steals": 2, "tpa": 12, "tpm": 5, "tppct": 41.7, "turnovers": null}, "displayName": "\u5bf9\u9635 \u7070\u718a", "name": "Against Mem"}, {"statAverage": {"assistsPg": 6.0, "blocksPg": 0.0, "defRebsPg": 5.0, "efficiency": null, "fgaPg": 15.0, "fgmPg": 6.0, "fgpct": 40.0, "foulsPg": null, "ftaPg": 3.0, "ftmPg": 3.0, "ftpct": 100.0, "games": 1, "gamesStarted": 1, "minsPg": 31.0, "offRebsPg": 1.0, "pointsPg": 17.0, "rebsPg": 6.0, "stealsPg": 4.0, "tpaPg": 6.0, "tpmPg": 2.0, "tppct": 33.3, "turnoversPg": null}, "statTotal": {"assists": 6, "blocks": 0, "defRebs": 5, "fga": 15, "fgm": 6, "fgpct": 40.0, "fouls": null, "fta": 3, "ftm": 3, "ftpct": 100.0, "mins": 0, "offRebs": 1, "points": 17, "rebs": 6, "secs": 0, "steals": 4, "tpa": 6, "tpm": 2, "tppct": 33.3, "turnovers": null}, "displayName": "\u5bf9\u9635 \u96c4\u9e7f", "name": "Against Mil"}, {"statAverage": {"assistsPg": 7.0, "blocksPg": 1.0, "defRebsPg": 6.0, "efficiency": null, "fgaPg": 33.0, "fgmPg": 17.0, "fgpct": 51.5, "foulsPg": null, "ftaPg": 10.0, "ftmPg": 9.0, "ftpct": 90.0, "games": 1, "gamesStarted": 1, "minsPg": 38.0, "offRebsPg": 2.0, "pointsPg": 50.0, "rebsPg": 8.0, "stealsPg": 0.0, "tpaPg": 14.0, "tpmPg": 7.0, "tppct": 50.0, "turnoversPg": null}, "statTotal": {"assists": 7, "blocks": 1, "defRebs": 6, "fga": 33, "fgm": 17, "fgpct": 51.5, "fouls": null, "fta": 10, "ftm": 9, "ftpct": 90.0, "mins": 0, "offRebs": 2, "points": 50, "rebs": 8, "secs": 0, "steals": 0, "tpa": 14, "tpm": 7, "tppct": 50.0, "turnovers": null}, "displayName": "\u5bf9\u9635 \u68ee\u6797\u72fc", "name": "Against Min"}, {"statAverage": {"assistsPg": 9.0, "blocksPg": 0.0, "defRebsPg": 3.0, "efficiency": null, "fgaPg": 21.0, "fgmPg": 13.0, "fgpct": 61.9, "foulsPg": null, "ftaPg": 11.0, "ftmPg": 11.0, "ftpct": 100.0, "games": 1, "gamesStarted": 1, "minsPg": 35.0, "offRebsPg": 1.0, "pointsPg": 39.0, "rebsPg": 4.0, "stealsPg": 3.0, "tpaPg": 6.0, "tpmPg": 2.0, "tppct": 33.3, "turnoversPg": null}, "statTotal": {"assists": 9, "blocks": 0, "defRebs": 3, "fga": 21, "fgm": 13, "fgpct": 61.9, "fouls": null, "fta": 11, "ftm": 11, "ftpct": 100.0, "mins": 0, "offRebs": 1, "points": 39, "rebs": 4, "secs": 0, "steals": 3, "tpa": 6, "tpm": 2, "tppct": 33.3, "turnovers": null}, "displayName": "\u5bf9\u9635 \u9e48\u9e55", "name": "Against NO"}, {"statAverage": {"assistsPg": 5.0, "blocksPg": 0.0, "defRebsPg": 1.0, "efficiency": null, "fgaPg": 19.0, "fgmPg": 8.0, "fgpct": 42.1, "foulsPg": null, "ftaPg": 8.0, "ftmPg": 8.0, "ftpct": 100.0, "games": 1, "gamesStarted": 1, "minsPg": 31.0, "offRebsPg": 1.0, "pointsPg": 26.0, "rebsPg": 2.0, "stealsPg": 3.0, "tpaPg": 8.0, "tpmPg": 2.0, "tppct": 25.0, "turnoversPg": null}, "statTotal": {"assists": 5, "blocks": 0, "defRebs": 1, "fga": 19, "fgm": 8, "fgpct": 42.1, "fouls": null, "fta": 8, "ftm": 8, "ftpct": 100.0, "mins": 0, "offRebs": 1, "points": 26, "rebs": 2, "secs": 0, "steals": 3, "tpa": 8, "tpm": 2, "tppct": 25.0, "turnovers": null}, "displayName": "\u5bf9\u9635 \u5c3c\u514b\u65af", "name": "Against NY"}, {"statAverage": {"assistsPg": 4.0, "blocksPg": 1.0, "defRebsPg": 3.0, "efficiency": null, "fgaPg": 21.0, "fgmPg": 6.0, "fgpct": 28.6, "foulsPg": null, "ftaPg": 2.0, "ftmPg": 1.0, "ftpct": 50.0, "games": 1, "gamesStarted": 1, "minsPg": 37.0, "offRebsPg": 3.0, "pointsPg": 14.0, "rebsPg": 6.0, "stealsPg": 2.0, "tpaPg": 2.0, "tpmPg": 1.0, "tppct": 50.0, "turnoversPg": null}, "statTotal": {"assists": 4, "blocks": 1, "defRebs": 3, "fga": 21, "fgm": 6, "fgpct": 28.6, "fouls": null, "fta": 2, "ftm": 1, "ftpct": 50.0, "mins": 0, "offRebs": 3, "points": 14, "rebs": 6, "secs": 0, "steals": 2, "tpa": 2, "tpm": 1, "tppct": 50.0, "turnovers": null}, "displayName": "\u5bf9\u9635 76\u4eba", "name": "Against Phi"}, {"statAverage": {"assistsPg": 5.0, "blocksPg": 0.0, "defRebsPg": 3.0, "efficiency": null, "fgaPg": 16.0, "fgmPg": 7.0, "fgpct": 43.8, "foulsPg": null, "ftaPg": 0.0, "ftmPg": 0.0, "ftpct": 0.0, "games": 1, "gamesStarted": 1, "minsPg": 25.0, "offRebsPg": 1.0, "pointsPg": 15.0, "rebsPg": 4.0, "stealsPg": 0.0, "tpaPg": 6.0, "tpmPg": 1.0, "tppct": 16.7, "turnoversPg": null}, "statTotal": {"assists": 5, "blocks": 0, "defRebs": 3, "fga": 16, "fgm": 7, "fgpct": 43.8, "fouls": null, "fta": 0, "ftm": 0, "ftpct": 0.0, "mins": 0, "offRebs": 1, "points": 15, "rebs": 4, "secs": 0, "steals": 0, "tpa": 6, "tpm": 1, "tppct": 16.7, "turnovers": null}, "displayName": "\u5bf9\u9635 \u592a\u9633", "name": "Against Pho"}, {"statAverage": {"assistsPg": 6.0, "blocksPg": 1.0, "defRebsPg": 2.0, "efficiency": null, "fgaPg": 27.0, "fgmPg": 12.0, "fgpct": 44.4, "foulsPg": null, "ftaPg": 5.0, "ftmPg": 5.0, "ftpct": 100.0, "games": 1, "gamesStarted": 1, "minsPg": 39.0, "offRebsPg": 1.0, "pointsPg": 33.0, "rebsPg": 3.0, "stealsPg": 1.0, "tpaPg": 8.0, "tpmPg": 4.0, "tppct": 50.0, "turnoversPg": null}, "statTotal": {"assists": 6, "blocks": 1, "defRebs": 2, "fga": 27, "fgm": 12, "fgpct": 44.4, "fouls": null, "fta": 5, "ftm": 5, "ftpct": 100.0, "mins": 0, "offRebs": 1, "points": 33, "rebs": 3, "secs": 0, "steals": 1, "tpa": 8, "tpm": 4, "tppct": 50.0, "turnovers": null}, "displayName": "\u5bf9\u9635 \u5f00\u62d3\u8005", "name": "Against Por"}, {"statAverage": {"assistsPg": 8.0, "blocksPg": 1.0, "defRebsPg": 2.5, "efficiency": null, "fgaPg": 24.5, "fgmPg": 11.0, "fgpct": 44.9, "foulsPg": null, "ftaPg": 5.5, "ftmPg": 5.0, "ftpct": 90.9, "games": 2, "gamesStarted": 2, "minsPg": 34.5, "offRebsPg": 1.5, "pointsPg": 29.5, "rebsPg": 4.0, "stealsPg": 1.5, "tpaPg": 8.5, "tpmPg": 2.5, "tppct": 29.4, "turnoversPg": null}, "statTotal": {"assists": 16, "blocks": 2, "defRebs": 5, "fga": 49, "fgm": 22, "fgpct": 44.9, "fouls": null, "fta": 11, "ftm": 10, "ftpct": 90.9, "mins": 0, "offRebs": 3, "points": 59, "rebs": 8, "secs": 0, "steals": 3, "tpa": 17, "tpm": 5, "tppct": 29.4, "turnovers": null}, "displayName": "\u5bf9\u9635 \u7235\u58eb", "name": "Against Utah"}, {"statAverage": {"assistsPg": 4.0, "blocksPg": 1.0, "defRebsPg": 2.0, "efficiency": null, "fgaPg": 12.0, "fgmPg": 5.0, "fgpct": 41.7, "foulsPg": null, "ftaPg": 0.0, "ftmPg": 0.0, "ftpct": 0.0, "games": 1, "gamesStarted": 1, "minsPg": 29.0, "offRebsPg": 2.0, "pointsPg": 11.0, "rebsPg": 4.0, "stealsPg": 1.0, "tpaPg": 5.0, "tpmPg": 1.0, "tppct": 20.0, "turnoversPg": null}, "statTotal": {"assists": 4, "blocks": 1, "defRebs": 2, "fga": 12, "fgm": 5, "fgpct": 41.7, "fouls": null, "fta": 0, "ftm": 0, "ftpct": 0.0, "mins": 0, "offRebs": 2, "points": 11, "rebs": 4, "secs": 0, "steals": 1, "tpa": 5, "tpm": 1, "tppct": 20.0, "turnovers": null}, "displayName": "\u5bf9\u9635 \u5947\u624d", "name": "Against Was"}, {"statAverage": {"assistsPg": 5.5, "blocksPg": 0.3, "defRebsPg": 4.5, "efficiency": null, "fgaPg": 18.8, "fgmPg": 9.5, "fgpct": 50.5, "foulsPg": null, "ftaPg": 4.6, "ftmPg": 4.3, "ftpct": 93.5, "games": 10, "gamesStarted": 10, "minsPg": 31.6, "offRebsPg": 1.1, "pointsPg": 25.6, "rebsPg": 5.6, "stealsPg": 1.5, "tpaPg": 6.0, "tpmPg": 2.3, "tppct": 38.3, "turnoversPg": null}, "statTotal": {"assists": 55, "blocks": 3, "defRebs": 45, "fga": 188, "fgm": 95, "fgpct": 50.5, "fouls": null, "fta": 46, "ftm": 43, "ftpct": 93.5, "mins": 0, "offRebs": 11, "points": 256, "rebs": 56, "secs": 0, "steals": 15, "tpa": 60, "tpm": 23, "tppct": 38.3, "turnovers": null}, "displayName": "\u8054\u76df", "name": "Conference"}, {"statAverage": {"assistsPg": 4.5, "blocksPg": 0.5, "defRebsPg": 2.0, "efficiency": null, "fgaPg": 20.0, "fgmPg": 7.0, "fgpct": 35.0, "foulsPg": null, "ftaPg": 5.0, "ftmPg": 4.5, "ftpct": 90.0, "games": 2, "gamesStarted": 2, "minsPg": 34.0, "offRebsPg": 2.0, "pointsPg": 20.0, "rebsPg": 4.0, "stealsPg": 2.5, "tpaPg": 5.0, "tpmPg": 1.5, "tppct": 30.0, "turnoversPg": null}, "statTotal": {"assists": 9, "blocks": 1, "defRebs": 4, "fga": 40, "fgm": 14, "fgpct": 35.0, "fouls": null, "fta": 10, "ftm": 9, "ftpct": 90.0, "mins": 0, "offRebs": 4, "points": 40, "rebs": 8, "secs": 0, "steals": 5, "tpa": 10, "tpm": 3, "tppct": 30.0, "turnovers": null}, "displayName": "\u5206\u533a", "name": "Division"}, {"statAverage": {"assistsPg": 4.0, "blocksPg": 1.0, "defRebsPg": 2.0, "efficiency": null, "fgaPg": 12.0, "fgmPg": 5.0, "fgpct": 41.7, "foulsPg": null, "ftaPg": 0.0, "ftmPg": 0.0, "ftpct": 0.0, "games": 1, "gamesStarted": 1, "minsPg": 29.0, "offRebsPg": 2.0, "pointsPg": 11.0, "rebsPg": 4.0, "stealsPg": 1.0, "tpaPg": 5.0, "tpmPg": 1.0, "tppct": 20.0, "turnoversPg": null}, "statTotal": {"assists": 4, "blocks": 1, "defRebs": 2, "fga": 12, "fgm": 5, "fgpct": 41.7, "fouls": null, "fta": 0, "ftm": 0, "ftpct": 0.0, "mins": 0, "offRebs": 2, "points": 11, "rebs": 4, "secs": 0, "steals": 1, "tpa": 5, "tpm": 1, "tppct": 20.0, "turnovers": null}, "displayName": "\u4e8c\u6708", "name": "February"}, {"statAverage": {"assistsPg": 6.5, "blocksPg": 0.6, "defRebsPg": 4.5, "efficiency": null, "fgaPg": 20.917, "fgmPg": 9.0, "fgpct": 43.0, "foulsPg": null, "ftaPg": 4.167, "ftmPg": 3.667, "ftpct": 88.0, "games": 12, "gamesStarted": 12, "minsPg": 32.9, "offRebsPg": 1.3, "pointsPg": 24.0, "rebsPg": 5.8, "stealsPg": 1.3, "tpaPg": 7.083, "tpmPg": 2.333, "tppct": 32.9, "turnoversPg": null}, "statTotal": {"assists": 78, "blocks": 8, "defRebs": 54, "fga": 251, "fgm": 108, "fgpct": 43.0, "fouls": null, "fta": 50, "ftm": 44, "ftpct": 88.0, "mins": 0, "offRebs": 16, "points": 288, "rebs": 70, "secs": 0, "steals": 16, "tpa": 85, "tpm": 28, "tppct": 32.9, "turnovers": null}, "displayName": "\u8d1f", "name": "Games Lost"}, {"statAverage": {"assistsPg": 6.2, "blocksPg": 0.2, "defRebsPg": 3.3, "efficiency": null, "fgaPg": 20.625, "fgmPg": 11.375, "fgpct": 55.2, "foulsPg": null, "ftaPg": 6.5, "ftmPg": 6.25, "ftpct": 96.2, "games": 8, "gamesStarted": 8, "minsPg": 32.8, "offRebsPg": 0.7, "pointsPg": 32.5, "rebsPg": 4.0, "stealsPg": 1.3, "tpaPg": 7.125, "tpmPg": 3.5, "tppct": 49.1, "turnoversPg": null}, "statTotal": {"assists": 50, "blocks": 2, "defRebs": 27, "fga": 165, "fgm": 91, "fgpct": 55.2, "fouls": null, "fta": 52, "ftm": 50, "ftpct": 96.2, "mins": 0, "offRebs": 6, "points": 260, "rebs": 33, "secs": 0, "steals": 11, "tpa": 57, "tpm": 28, "tppct": 49.1, "turnovers": null}, "displayName": "\u80dc", "name": "Games Won"}, {"statAverage": {"assistsPg": 6.4, "blocksPg": 0.4, "defRebsPg": 3.8, "efficiency": null, "fgaPg": 19.273, "fgmPg": 10.636, "fgpct": 55.2, "foulsPg": null, "ftaPg": 5.909, "ftmPg": 5.364, "ftpct": 90.8, "games": 11, "gamesStarted": 11, "minsPg": 31.8, "offRebsPg": 1.0, "pointsPg": 29.9, "rebsPg": 4.8, "stealsPg": 1.7, "tpaPg": 6.727, "tpmPg": 3.273, "tppct": 48.6, "turnoversPg": null}, "statTotal": {"assists": 71, "blocks": 5, "defRebs": 42, "fga": 212, "fgm": 117, "fgpct": 55.2, "fouls": null, "fta": 65, "ftm": 59, "ftpct": 90.8, "mins": 0, "offRebs": 11, "points": 329, "rebs": 53, "secs": 0, "steals": 19, "tpa": 74, "tpm": 36, "tppct": 48.6, "turnovers": null}, "displayName": "\u4e3b\u573a", "name": "Home"}, {"statAverage": {"assistsPg": 5.6, "blocksPg": 0.3, "defRebsPg": 3.7, "efficiency": null, "fgaPg": 19.0, "fgmPg": 10.25, "fgpct": 53.9, "foulsPg": null, "ftaPg": 4.875, "ftmPg": 4.375, "ftpct": 89.7, "games": 8, "gamesStarted": 8, "minsPg": 32.1, "offRebsPg": 1.2, "pointsPg": 27.8, "rebsPg": 4.9, "stealsPg": 1.7, "tpaPg": 5.75, "tpmPg": 3.0, "tppct": 52.2, "turnoversPg": null}, "statTotal": {"assists": 45, "blocks": 3, "defRebs": 30, "fga": 152, "fgm": 82, "fgpct": 53.9, "fouls": null, "fta": 39, "ftm": 35, "ftpct": 89.7, "mins": 0, "offRebs": 10, "points": 223, "rebs": 40, "secs": 0, "steals": 14, "tpa": 46, "tpm": 24, "tppct": 52.2, "turnovers": null}, "displayName": "\u4e00\u6708", "name": "January"}, {"statAverage": {"assistsPg": 5.8, "blocksPg": 0.4, "defRebsPg": 3.7, "efficiency": null, "fgaPg": 18.4, "fgmPg": 9.5, "fgpct": 51.6, "foulsPg": null, "ftaPg": 3.9, "ftmPg": 3.5, "ftpct": 89.7, "games": 10, "gamesStarted": 10, "minsPg": 32.1, "offRebsPg": 1.3, "pointsPg": 25.1, "rebsPg": 5.0, "stealsPg": 1.6, "tpaPg": 5.6, "tpmPg": 2.6, "tppct": 46.4, "turnoversPg": null}, "statTotal": {"assists": 58, "blocks": 4, "defRebs": 37, "fga": 184, "fgm": 95, "fgpct": 51.6, "fouls": null, "fta": 39, "ftm": 35, "ftpct": 89.7, "mins": 0, "offRebs": 13, "points": 251, "rebs": 50, "secs": 0, "steals": 16, "tpa": 56, "tpm": 26, "tppct": 46.4, "turnovers": null}, "displayName": "\u6700\u8fd1\u5341\u573a\u6bd4\u8d5b", "name": "Last 10 Games"}, {"statAverage": {"assistsPg": 5.0, "blocksPg": 0.4, "defRebsPg": 3.4, "efficiency": null, "fgaPg": 19.6, "fgmPg": 10.6, "fgpct": 54.1, "foulsPg": 3.2, "ftaPg": 5.6, "ftmPg": 5.2, "ftpct": 92.9, "games": 5, "gamesStarted": 5, "minsPg": 33.4, "offRebsPg": 1.2, "pointsPg": 30.0, "rebsPg": 4.6, "stealsPg": 1.2, "tpaPg": 7.4, "tpmPg": 3.6, "tppct": 48.6, "turnoversPg": 3.8}, "statTotal": {"assists": 25, "blocks": 2, "defRebs": 17, "fga": 98, "fgm": 53, "fgpct": 54.1, "fouls": 16, "fta": 28, "ftm": 26, "ftpct": 92.9, "mins": 0, "offRebs": 6, "points": 150, "rebs": 23, "secs": 0, "steals": 6, "tpa": 37, "tpm": 18, "tppct": 48.6, "turnovers": 19}, "displayName": "\u6700\u8fd1\u4e94\u573a\u6bd4\u8d5b", "name": "Last 5 Games"}, {"statAverage": {"assistsPg": 7.7, "blocksPg": 0.4, "defRebsPg": 4.1, "efficiency": null, "fgaPg": 21.857, "fgmPg": 9.286, "fgpct": 42.5, "foulsPg": null, "ftaPg": 4.143, "ftmPg": 4.0, "ftpct": 96.6, "games": 7, "gamesStarted": 7, "minsPg": 33.8, "offRebsPg": 0.8, "pointsPg": 24.7, "rebsPg": 4.9, "stealsPg": 0.8, "tpaPg": 7.286, "tpmPg": 2.143, "tppct": 29.4, "turnoversPg": null}, "statTotal": {"assists": 54, "blocks": 3, "defRebs": 29, "fga": 153, "fgm": 65, "fgpct": 42.5, "fouls": null, "fta": 29, "ftm": 28, "ftpct": 96.6, "mins": 0, "offRebs": 6, "points": 173, "rebs": 35, "secs": 0, "steals": 6, "tpa": 51, "tpm": 15, "tppct": 29.4, "turnovers": null}, "displayName": "\u5341\u4e00\u6708", "name": "November"}, {"statAverage": {"assistsPg": 6.2, "blocksPg": 0.7, "defRebsPg": 5.0, "efficiency": null, "fgaPg": 24.75, "fgmPg": 11.75, "fgpct": 47.5, "foulsPg": null, "ftaPg": 8.5, "ftmPg": 7.75, "ftpct": 91.2, "games": 4, "gamesStarted": 4, "minsPg": 33.7, "offRebsPg": 1.0, "pointsPg": 35.2, "rebsPg": 6.0, "stealsPg": 1.5, "tpaPg": 10.0, "tpmPg": 4.0, "tppct": 40.0, "turnoversPg": null}, "statTotal": {"assists": 25, "blocks": 3, "defRebs": 20, "fga": 99, "fgm": 47, "fgpct": 47.5, "fouls": null, "fta": 34, "ftm": 31, "ftpct": 91.2, "mins": 0, "offRebs": 4, "points": 141, "rebs": 24, "secs": 0, "steals": 6, "tpa": 40, "tpm": 16, "tppct": 40.0, "turnovers": null}, "displayName": "\u5341\u6708", "name": "October"}, {"statAverage": {"assistsPg": 6.3, "blocksPg": 0.5, "defRebsPg": 4.3, "efficiency": null, "fgaPg": 22.667, "fgmPg": 9.111, "fgpct": 40.2, "foulsPg": null, "ftaPg": 4.111, "ftmPg": 3.889, "ftpct": 94.6, "games": 9, "gamesStarted": 9, "minsPg": 34.2, "offRebsPg": 1.2, "pointsPg": 24.3, "rebsPg": 5.5, "stealsPg": 0.8, "tpaPg": 7.556, "tpmPg": 2.222, "tppct": 29.4, "turnoversPg": null}, "statTotal": {"assists": 57, "blocks": 5, "defRebs": 39, "fga": 204, "fgm": 82, "fgpct": 40.2, "fouls": null, "fta": 37, "ftm": 35, "ftpct": 94.6, "mins": 0, "offRebs": 11, "points": 219, "rebs": 50, "secs": 0, "steals": 8, "tpa": 68, "tpm": 20, "tppct": 29.4, "turnovers": null}, "displayName": "\u5ba2\u573a", "name": "Road"}, {"statAverage": {"assistsPg": 6.4, "blocksPg": 0.5, "defRebsPg": 4.0, "efficiency": null, "fgaPg": 20.8, "fgmPg": 9.95, "fgpct": 47.8, "foulsPg": null, "ftaPg": 5.1, "ftmPg": 4.7, "ftpct": 92.2, "games": 20, "gamesStarted": 20, "minsPg": 32.9, "offRebsPg": 1.1, "pointsPg": 27.4, "rebsPg": 5.1, "stealsPg": 1.3, "tpaPg": 7.1, "tpmPg": 2.8, "tppct": 39.4, "turnoversPg": null}, "statTotal": {"assists": 128, "blocks": 10, "defRebs": 81, "fga": 416, "fgm": 199, "fgpct": 47.8, "fouls": null, "fta": 102, "ftm": 94, "ftpct": 92.2, "mins": 0, "offRebs": 22, "points": 548, "rebs": 103, "secs": 0, "steals": 27, "tpa": 142, "tpm": 56, "tppct": 39.4, "turnovers": null}, "displayName": "\u5148\u53d1", "name": "Starter"}], "last5Games": {"statAverage": {"assistsPg": 5.0, "blocksPg": 0.4, "defRebsPg": 3.4, "efficiency": null, "fgaPg": 19.6, "fgmPg": 10.6, "fgpct": 54.1, "foulsPg": 3.2, "ftaPg": 5.6, "ftmPg": 5.2, "ftpct": 92.9, "games": 5, "gamesStarted": 5, "minsPg": 33.4, "offRebsPg": 1.2, "pointsPg": 30.0, "rebsPg": 4.6, "stealsPg": 1.2, "tpaPg": 7.4, "tpmPg": 3.6, "tppct": 48.6, "turnoversPg": 3.8}, "statTotal": {"assists": 25, "blocks": 2, "defRebs": 17, "fga": 98, "fgm": 53, "fgpct": 54.1, "fouls": 16, "fta": 28, "ftm": 26, "ftpct": 92.9, "mins": 167, "offRebs": 6, "points": 150, "rebs": 23, "secs": 154, "steals": 6, "tpa": 37, "tpm": 18, "tppct": 48.6, "turnovers": 19}}}}}}, "timestamp": "1586883949478"}